Workbook
Name Slicer_Category: #N/A
Name Slicer_Month: #N/A
Name Slicer_State: #N/A

Sheet Zudio_sales_data (2)
A1: State | B1: City | C1: Category | D1: Clothing Type | E1: Store Number | F1: Postal Code | G1: Store Type | H1: Store Open Date | I1: Selling Area Size | J1: Store Manager | K1: Manager ID | L1: Store Address | M1: Contact Information | N1: Operating Hours | O1: Staff Count | P1: Parking Availability | Q1: Security Features | R1: Order ID | S1: Order Date | T1: Month | U1: Customer ID | V1: Customer Name | W1: Product ID | X1: Price | Y1: Quantity | Z1: Sales | AA1: Digits | AB1: CleanDigits | AC1: Length | AD1: Mobile Check | AE1: Landline Check | AF1: Contact Type | AG1: Final Contact
A2: Gujarat | B2: Patna | C2: Kids | D2: Skirts | E2: 48 | F2: 404562 | G2: Owned | H2: 44184 | I2: 1200 | J2: Deborah Jackson | K2: M89 | L2: 0189 Anthony Stravenue Apt. 861 Maryhaven, WV 77722 | M2: 18387102029 | N2: 10 AM - 9 PM | O2: 6 | P2: Not Available | Q2: Alarm | R2: 78145 | S2: 45460 | T2: June | U2: 926472 | V2: Daniel Jimenez | W2: 741 | X2: 2078 | Y2: 1 | Z2: 831.2 | AA2: 18387102029 | AB2: 18387102029 | AC2: 11 | AE2: Landline | AF2: Landline | AG2: 18387102029
A3: West Bengal | B3: Guwahati | C3: Men | D3: Dresses | E3: 51 | F3: 415370 | G3: Owned | H3: 44710 | I3: 1400 | J3: Matthew Romero | K3: M24 | L3: 0557 Cameron Trail Apt. 690 South Samuel, TX 36835 | M3: 3361476341 | N3: 10 AM - 7 PM | O3: 19 | P3: Not Available | Q3: CCTV, Alarm | R3: 58242 | S3: 45390 | T3: April | U3: 264070 | V3: Victor Arnold | W3: 479 | X3: 1105 | Y3: 6 | Z3: 2652 | AA3: 3361476341 | AB3: 3361476341 | AC3: 10 | AE3: Landline | AF3: Landline | AG3: 3361476341
A4: West Bengal | B4: Nashik | C4: Kids | D4: Jackets | E4: 71 | F4: 417269 | G4: Owned | H4: 44364 | I4: 800 | J4: Chelsea Hill | K4: M14 | L4: 3318 Carter Burgs Apt. 327 North Richardshire, CT 47189 | M4: 11490005823 | N4: 9 AM - 8 PM | O4: 14 | P4: Available | Q4: CCTV | R4: 78800 | S4: 45407 | T4: April | U4: 326466 | V4: James Bennett | W4: 295 | X4: 2206 | Y4: 4 | Z4: 3529.6 | AA4: 11490005823 | AB4: 11490005823 | AC4: 11 | AE4: Landline | AF4: Landline | AG4: 11490005823
A5: West Bengal | B5: Hyderabad | C5: Women | D5: Tops | E5: 74 | F5: 417964 | G5: Owned | H5: 44516 | I5: 950 | J5: Denise Molina | K5: M54 | L5: 75265 Taylor Stream Suite 679 Juarezview, ID 78431 | M5: 6468999850 | N5: 10 AM - 9 PM | O5: 18 | P5: Available | Q5: CCTV | R5: 23062 | S5: 45454 | T5: June | U5: 870587 | V5: Matthew Cervantes | W5: 595 | X5: 1694 | Y5: 8 | Z5: 5420.8 | AA5: 6468999850 | AB5: 6468999850 | AC5: 10 | AD5: Mobile | AF5: Mobile | AG5: 6468999850
A6: Uttar Pradesh | B6: Nashik | C6: Men | D6: Jackets | E6: 90 | F6: 411552 | G6: Rented | H6: 44905 | I6: 1000 | J6: Brian Ruiz | K6: M31 | L6: 06314 Sanders Brook North Ginaton, SD 13921 | M6: 5358716788 | N6: 10 AM - 9 PM | O6: 11 | P6: Available | Q6: None | R6: 84854 | S6: 45495 | T6: July | U6: 151454 | V6: Thomas Lin | W6: 878 | X6: 2839 | Y6: 1 | Z6: 1135.6 | AA6: 5358716788 | AB6: 5358716788 | AC6: 10 | AE6: Landline | AF6: Landline | AG6: 5358716788
A7: Rajasthan | B7: Bengaluru | C7: Women | D7: Hoodies | E7: 43 | F7: 423063 | G7: Owned | H7: 44216 | I7: 1400 | J7: Sandra Burns | K7: M75 | L7: 468 Courtney Trail Apt. 647 Dominiqueside, SD 35375 | M7: 4312762356 | N7: 11 AM - 8 PM | O7: 8 | P7: Available | Q7: CCTV, Alarm | R7: 76134 | S7: 45492 | T7: July | U7: 908342 | V7: Shannon Kelly | W7: 895 | X7: 2299 | Y7: 3 | Z7: 2758.8 | AA7: 4312762356 | AB7: 4312762356 | AC7: 10 | AE7: Landline | AF7: Landline | AG7: 4312762356
A8: Delhi | B8: Patna | C8: Kids | D8: Dresses | E8: 49 | F8: 417553 | G8: Owned | H8: 45470 | I8: 1000 | J8: Jeffrey Boyle | K8: M19 | L8: 8844 Robert Club Apt. 926 North Williamborough, SC 12197 | M8: 9848475274 | N8: 11 AM - 8 PM | O8: 8 | P8: Not Available | Q8: None | R8: 74430 | S8: 45422 | T8: May | U8: 175073 | V8: Tonya Manning | W8: 970 | X8: 2249 | Y8: 3 | Z8: 2698.8 | AA8: 9848475274 | AB8: 9848475274 | AC8: 10 | AD8: Mobile | AF8: Mobile | AG8: 9848475274
A9: Karnataka | B9: Bengaluru | C9: Women | D9: Tops | E9: 15 | F9: 424173 | G9: Rented | H9: 44347 | I9: 1100 | J9: Donald Horton | K9: M27 | L9: Unit 5604 Box 6098 DPO AP 20626 | M9: 7897488733 | N9: 11 AM - 8 PM | O9: 13 | P9: Not Available | Q9: CCTV, Alarm | R9: 77434 | S9: 45309 | T9: January | U9: 291736 | V9: Donna Rodriguez | W9: 693 | X9: 1764 | Y9: 1 | Z9: 705.6 | AA9: 7897488733 | AB9: 7897488733 | AC9: 10 | AD9: Mobile | AF9: Mobile | AG9: 7897488733
A10: Karnataka | B10: Chandigarh | C10: Women | D10: Sweaters | E10: 1 | F10: 422109 | G10: Owned | H10: 45279 | I10: 1200 | J10: Daniel Marshall | K10: M59 | L10: PSC 5996, Box 0535 APO AP 11034 | M10: 7161897958 | N10: 9 AM - 8 PM | O10: 3 | P10: Available | Q10: Alarm | R10: 16226 | S10: 45387 | T10: April | U10: 858667 | V10: Michelle Torres | W10: 206 | X10: 2411 | Y10: 4 | Z10: 3857.6 | AA10: 7161897958 | AB10: 7161897958 | AC10: 10 | AD10: Mobile | AF10: Mobile | AG10: 7161897958
A11: Gujarat | B11: Ranchi | C11: Men | D11: Skirts | E11: 25 | F11: 435701 | G11: Rented | H11: 44001 | I11: 800 | J11: Marc Taylor | K11: M84 | L11: PSC 8659, Box 8391 APO AA 17496 | M11: 14147126135 | N11: 10 AM - 9 PM | O11: 4 | P11: Available | Q11: CCTV | R11: 91338 | S11: 45601 | T11: November | U11: 113822 | V11: Angela Buckley | W11: 288 | X11: 2519 | Y11: 2 | Z11: 2015.2 | AA11: 14147126135 | AB11: 14147126135 | AC11: 11 | AE11: Landline | AF11: Landline | AG11: 14147126135
A12: Karnataka | B12: Agra | C12: Kids | D12: Hoodies | E12: 13 | F12: 436327 | G12: Rented | H12: 45364 | I12: 1100 | J12: Julia Pruitt | K12: M5 | L12: 285 James Underpass Apt. 258 Martinland, OH 31985 | M12: 2527892394 | N12: 11 AM - 8 PM | O12: 8 | P12: Available | Q12: Alarm | R12: 66941 | S12: 45580 | T12: October | U12: 453482 | V12: Monica Meyer | W12: 697 | X12: 1524 | Y12: 6 | Z12: 3657.6 | AA12: 2527892394 | AB12: 2527892394 | AC12: 10 | AE12: Landline | AF12: Landline | AG12: 2527892394
A13: Maharashtra | B13: Jalna | C13: Women | D13: Hoodies | E13: 62 | F13: 437619 | G13: Rented | H13: 43920 | I13: 800 | J13: Courtney White | K13: M95 | L13: 013 Timothy Tunnel Suite 710 Mauricetown, NH 39270 | M13: 1924195193 | N13: 10 AM - 9 PM | O13: 10 | P13: Available | Q13: Alarm | R13: 36217 | S13: 45590 | T13: October | U13: 898096 | V13: Morgan Gonzales | W13: 512 | X13: 1089 | Y13: 2 | Z13: 871.2 | AA13: 1924195193 | AB13: 1924195193 | AC13: 10 | AE13: Landline | AF13: Landline | AG13: 1924195193
A14: Rajasthan | B14: Vadodara | C14: Men | D14: Jackets | E14: 78 | F14: 409258 | G14: Rented | H14: 44952 | I14: 950 | J14: Tammy Lopez | K14: M47 | L14: 19303 Kaitlyn Club South Rose, SC 87962 | M14: 7301627414 | N14: 10 AM - 9 PM | O14: 10 | P14: Available | Q14: None | R14: 89182 | S14: 45508 | T14: August | U14: 214027 | V14: Timothy Jackson | W14: 783 | X14: 1977 | Y14: 2 | Z14: 1581.6 | AA14: 7301627414 | AB14: 7301627414 | AC14: 10 | AD14: Mobile | AF14: Mobile | AG14: 7301627414
A15: Delhi | B15: Varanasi | C15: Kids | D15: Pants | E15: 55 | F15: 423944 | G15: Owned | H15: 44368 | I15: 1400 | J15: Andrew James | K15: M35 | L15: 3538 Lindsey Roads Apt. 818 New Samuel, CA 78166 | M15: 15643551557 | N15: 10 AM - 7 PM | O15: 14 | P15: Available | Q15: CCTV | R15: 30076 | S15: 45560 | T15: September | U15: 961724 | V15: Connie Cox | W15: 477 | X15: 2918 | Y15: 6 | Z15: 7003.2 | AA15: 15643551557 | AB15: 15643551557 | AC15: 11 | AE15: Landline | AF15: Landline | AG15: 15643551557
A16: Gujarat | B16: Indore | C16: Women | D16: Jeans | E16: 13 | F16: 403154 | G16: Owned | H16: 44927 | I16: 1000 | J16: Erin Conner | K16: M44 | L16: 630 Anderson Valley Carlymouth, KY 77205 | M16: 4833326287 | N16: 10 AM - 9 PM | O16: 18 | P16: Available | Q16: CCTV | R16: 72434 | S16: 45531 | T16: August | U16: 406764 | V16: Jenny Montgomery | W16: 258 | X16: 569 | Y16: 1 | Z16: 227.6 | AA16: 4833326287 | AB16: 4833326287 | AC16: 10 | AE16: Landline | AF16: Landline | AG16: 4833326287
A17: Gujarat | B17: Mysuru | C17: Kids | D17: Pants | E17: 34 | F17: 406635 | G17: Owned | H17: 44242 | I17: 1300 | J17: Kathleen Acevedo | K17: M58 | L17: 40699 Michael Springs East Patricia, NM 81150 | M17: 2583561368 | N17: 10 AM - 9 PM | O17: 9 | P17: Available | Q17: None | R17: 51465 | S17: 45533 | T17: August | U17: 351201 | V17: Clarence Turner | W17: 629 | X17: 2878 | Y17: 6 | Z17: 6907.2 | AA17: 2583561368 | AB17: 2583561368 | AC17: 10 | AE17: Landline | AF17: Landline | AG17: 2583561368
A18: Rajasthan | B18: Bhopal | C18: Women | D18: Shirts | E18: 60 | F18: 416049 | G18: Owned | H18: 45427 | I18: 950 | J18: Patricia Brock | K18: M33 | L18: 8677 Michael Key West Dwaynefurt, MD 34063 | M18: 0700431033 | N18: 11 AM - 8 PM | O18: 8 | P18: Not Available | Q18: CCTV | R18: 38355 | S18: 45613 | T18: November | U18: 917117 | V18: Jody Stewart | W18: 279 | X18: 1469 | Y18: 1 | Z18: 587.6 | AA18: 0700431033 | AB18: 0700431033 | AC18: 10 | AE18: Landline | AF18: Landline | AG18: 0700431033
A19: Karnataka | B19: Vadodara | C19: Women | D19: Pants | E19: 34 | F19: 431715 | G19: Owned | H19: 44281 | I19: 1200 | J19: Donna Mccoy | K19: M81 | L19: 0699 Jose Rapid Suite 698 New Ryan, WY 97159 | M19: 4672463976 | N19: 10 AM - 9 PM | O19: 19 | P19: Available | Q19: None | R19: 70815 | S19: 45360 | T19: March | U19: 154791 | V19: Kelly Smith DDS | W19: 426 | X19: 1132 | Y19: 4 | Z19: 1811.2 | AA19: 4672463976 | AB19: 4672463976 | AC19: 10 | AE19: Landline | AF19: Landline | AG19: 4672463976
A20: Maharashtra | B20: Chennai | C20: Kids | D20: Hoodies | E20: 2 | F20: 417599 | G20: Owned | H20: 45489 | I20: 1000 | J20: Dennis Price | K20: M28 | L20: 718 Alyssa Vista North Jacobburgh, CT 22192 | M20: 9368518073 | N20: 10 AM - 9 PM | O20: 5 | P20: Available | Q20: Alarm | R20: 57277 | S20: 45471 | T20: June | U20: 530727 | V20: Keith Smith | W20: 497 | X20: 908 | Y20: 3 | Z20: 1089.6 | AA20: 9368518073 | AB20: 9368518073 | AC20: 10 | AD20: Mobile | AF20: Mobile | AG20: 9368518073
A21: Rajasthan | B21: Jalna | C21: Women | D21: Jeans | E21: 4 | F21: 410819 | G21: Owned | H21: 44471 | I21: 950 | J21: Daisy Hayes | K21: M36 | L21: USCGC Jacobson FPO AA 42980 | M21: 4856502727 | N21: 10 AM - 9 PM | O21: 13 | P21: Not Available | Q21: Alarm | R21: 73749 | S21: 45360 | T21: March | U21: 175054 | V21: John Jordan | W21: 718 | X21: 2074 | Y21: 4 | Z21: 3318.4 | AA21: 4856502727 | AB21: 4856502727 | AC21: 10 | AE21: Landline | AF21: Landline | AG21: 4856502727
A22: Gujarat | B22: Bengaluru | C22: Women | D22: Shirts | E22: 92 | F22: 423320 | G22: Rented | H22: 44857 | I22: 1400 | J22: Katie Hernandez | K22: M98 | L22: 207 Denise Cliff Apt. 335 Port Scottshire, GA 88867 | M22: 8165661517 | N22: 10 AM - 9 PM | O22: 19 | P22: Available | Q22: Alarm | R22: 32188 | S22: 45400 | T22: April | U22: 262042 | V22: Jennifer Barrera | W22: 919 | X22: 820 | Y22: 4 | Z22: 1312 | AA22: 8165661517 | AB22: 8165661517 | AC22: 10 | AD22: Mobile | AF22: Mobile | AG22: 8165661517
A23: Rajasthan | B23: Kanpur | C23: Women | D23: Jackets | E23: 95 | F23: 420930 | G23: Owned | H23: 44198 | I23: 1100 | J23: Monique Harris | K23: M37 | L23: USCGC Williams FPO AA 72236 | M23: 2413227659 | N23: 9 AM - 8 PM | O23: 7 | P23: Available | Q23: CCTV, Alarm | R23: 68727 | S23: 45315 | T23: January | U23: 947806 | V23: Susan Hill | W23: 675 | X23: 1740 | Y23: 6 | Z23: 4176 | AA23: 2413227659 | AB23: 2413227659 | AC23: 10 | AE23: Landline | AF23: Landline | AG23: 2413227659
A24: Karnataka | B24: Hyderabad | C24: Women | D24: Jackets | E24: 59 | F24: 400656 | G24: Rented | H24: 44241 | I24: 1100 | J24: Kenneth Roberts | K24: M85 | L24: 92459 Reese River North Amberville, NJ 96825 | M24: 7653225577 | N24: 11 AM - 8 PM | O24: 13 | P24: Available | Q24: Alarm | R24: 37709 | S24: 45531 | T24: August | U24: 149403 | V24: Angel Booth | W24: 923 | X24: 2050 | Y24: 6 | Z24: 4920 | AA24: 7653225577 | AB24: 7653225577 | AC24: 10 | AD24: Mobile | AF24: Mobile | AG24: 7653225577
A25: Rajasthan | B25: Bengaluru | C25: Men | D25: Skirts | E25: 11 | F25: 401894 | G25: Owned | H25: 43915 | I25: 1200 | J25: Jennifer French | K25: M56 | L25: 11157 Jessica Avenue East Robertchester, GA 34955 | M25: 0034568233 | N25: 9 AM - 8 PM | O25: 18 | P25: Not Available | Q25: None | R25: 66994 | S25: 45340 | T25: February | U25: 511838 | V25: Ms. Mary Horton | W25: 993 | X25: 1835 | Y25: 6 | Z25: 4404 | AA25: 0034568233 | AB25: 0034568233 | AC25: 10 | AE25: Landline | AF25: Landline | AG25: 0034568233
A26: Delhi | B26: Faridabad | C26: Women | D26: Skirts | E26: 100 | F26: 405273 | G26: Rented | H26: 44492 | I26: 1400 | J26: Mr. Christian Baker | K26: M86 | L26: 522 Shelley Fort Suite 210 New Nancy, NM 37864 | M26: 7897018130 | N26: 10 AM - 9 PM | O26: 3 | P26: Available | Q26: Alarm | R26: 97689 | S26: 45477 | T26: July | U26: 923374 | V26: Reginald Cook | W26: 452 | X26: 1333 | Y26: 7 | Z26: 3732.4 | AA26: 7897018130 | AB26: 7897018130 | AC26: 10 | AD26: Mobile | AF26: Mobile | AG26: 7897018130
A27: Tamil Nadu | B27: Varanasi | C27: Women | D27: Hoodies | E27: 89 | F27: 429643 | G27: Owned | H27: 45377 | I27: 1100 | J27: Bruce Odonnell | K27: M52 | L27: 435 Jennifer Curve Suite 028 Jessicaside, MS 33050 | M27: 5169534444 | N27: 10 AM - 7 PM | O27: 8 | P27: Available | Q27: None | R27: 17973 | S27: 45379 | T27: March | U27: 452606 | V27: Steve Gibson | W27: 942 | X27: 2330 | Y27: 6 | Z27: 5592 | AA27: 5169534444 | AB27: 5169534444 | AC27: 10 | AE27: Landline | AF27: Landline | AG27: 5169534444
A28: Rajasthan | B28: Pondicherry | C28: Women | D28: Dresses | E28: 11 | F28: 404646 | G28: Owned | H28: 43845 | I28: 800 | J28: James Brooks | K28: M76 | L28: 85356 Cory Estate Apt. 775 Davistown, CO 65845 | M28: 8889238687 | N28: 10 AM - 7 PM | O28: 16 | P28: Available | Q28: None | R28: 32061 | S28: 45592 | T28: October | U28: 580394 | V28: Travis Shaffer | W28: 244 | X28: 2711 | Y28: 1 | Z28: 1084.4 | AA28: 8889238687 | AB28: 8889238687 | AC28: 10 | AD28: Mobile | AF28: Mobile | AG28: 8889238687
A29: Rajasthan | B29: Goa | C29: Women | D29: Shirts | E29: 91 | F29: 402039 | G29: Owned | H29: 44344 | I29: 1000 | J29: Angela Larson | K29: M3 | L29: 4541 Foster Fall Apt. 037 East Mark, CT 21382 | M29: 1421428778 | N29: 10 AM - 9 PM | O29: 11 | P29: Available | Q29: None | R29: 16607 | S29: 45627 | T29: December | U29: 711195 | V29: Abigail Coleman | W29: 928 | X29: 2725 | Y29: 8 | Z29: 8720 | AA29: 1421428778 | AB29: 1421428778 | AC29: 10 | AE29: Landline | AF29: Landline | AG29: 1421428778
A30: Tamil Nadu | B30: Thane | C30: Men | D30: Shoes | E30: 56 | F30: 413637 | G30: Owned | H30: 45225 | I30: 1200 | J30: Richard Bryan | K30: M85 | L30: 239 Elizabeth Canyon Suite 939 South Monique, ID 66968 | M30: 19671352682 | N30: 11 AM - 8 PM | O30: 3 | P30: Available | Q30: CCTV | R30: 46070 | S30: 45496 | T30: July | U30: 972849 | V30: Abigail Wright | W30: 277 | X30: 2608 | Y30: 1 | Z30: 1043.2 | AA30: 19671352682 | AB30: 19671352682 | AC30: 11 | AE30: Landline | AF30: Landline | AG30: 19671352682
A31: Karnataka | B31: Pune | C31: Men | D31: Shoes | E31: 76 | F31: 414806 | G31: Rented | H31: 45524 | I31: 1400 | J31: Rachel Oliver | K31: M21 | L31: 154 Christopher Forges South Joshua, KS 23568 | M31: 7644738567 | N31: 10 AM - 7 PM | O31: 20 | P31: Not Available | Q31: CCTV | R31: 58245 | S31: 45403 | T31: April | U31: 624117 | V31: George Santos | W31: 970 | X31: 2157 | Y31: 1 | Z31: 862.8 | AA31: 7644738567 | AB31: 7644738567 | AC31: 10 | AD31: Mobile | AF31: Mobile | AG31: 7644738567
A32: Rajasthan | B32: Visakhapatnam | C32: Men | D32: Shoes | E32: 10 | F32: 400259 | G32: Owned | H32: 45096 | I32: 1400 | J32: Rodney Flowers | K32: M29 | L32: 115 Lauren Cove West Scottfort, MD 64508 | M32: 16773954993 | N32: 10 AM - 7 PM | O32: 6 | P32: Available | Q32: CCTV | R32: 38044 | S32: 45609 | T32: November | U32: 691171 | V32: Joel Allen | W32: 510 | X32: 2134 | Y32: 5 | Z32: 4268 | AA32: 16773954993 | AB32: 16773954993 | AC32: 11 | AE32: Landline | AF32: Landline | AG32: 16773954993
A33: Uttar Pradesh | B33: Pondicherry | C33: Kids | D33: Skirts | E33: 66 | F33: 412685 | G33: Rented | H33: 44387 | I33: 1100 | J33: Christopher Le | K33: M96 | L33: 4641 Daniel Fall West Amandastad, MN 79578 | M33: 2232672202 | N33: 10 AM - 7 PM | O33: 5 | P33: Not Available | Q33: Alarm | R33: 12602 | S33: 45447 | T33: June | U33: 654281 | V33: David Mooney | W33: 733 | X33: 1013 | Y33: 3 | Z33: 1215.6 | AA33: 2232672202 | AB33: 2232672202 | AC33: 10 | AE33: Landline | AF33: Landline | AG33: 2232672202
A34: Rajasthan | B34: Aurangabad | C34: Men | D34: Dresses | E34: 59 | F34: 406021 | G34: Owned | H34: 44509 | I34: 1300 | J34: Sarah Brown | K34: M91 | L34: 9694 Paul Junctions Gregorystad, AR 04774 | M34: 6371765725 | N34: 9 AM - 8 PM | O34: 5 | P34: Not Available | Q34: None | R34: 92213 | S34: 45547 | T34: September | U34: 319126 | V34: Shawn Jones | W34: 558 | X34: 1297 | Y34: 1 | Z34: 518.8 | AA34: 6371765725 | AB34: 6371765725 | AC34: 10 | AD34: Mobile | AF34: Mobile | AG34: 6371765725
A35: Delhi | B35: Bhopal | C35: Women | D35: Dresses | E35: 94 | F35: 414625 | G35: Owned | H35: 43938 | I35: 1400 | J35: Judith Ayers | K35: M83 | L35: Unit 3901 Box 0286 DPO AP 67783 | M35: 8764525424 | N35: 10 AM - 7 PM | O35: 5 | P35: Available | Q35: CCTV | R35: 66724 | S35: 45376 | T35: March | U35: 894301 | V35: Krista Boyer | W35: 374 | X35: 2800 | Y35: 6 | Z35: 6720 | AA35: 8764525424 | AB35: 8764525424 | AC35: 10 | AD35: Mobile | AF35: Mobile | AG35: 8764525424
A36: Tamil Nadu | B36: Patna | C36: Men | D36: Dresses | E36: 17 | F36: 410757 | G36: Owned | H36: 45460 | I36: 950 | J36: Sherry Andrews | K36: M18 | L36: 73245 Dougherty Prairie Apt. 870 North Kendraport, OR 20268 | M36: 3671398866 | N36: 11 AM - 8 PM | O36: 4 | P36: Available | Q36: Alarm | R36: 86786 | S36: 45596 | T36: October | U36: 604698 | V36: Brittany Blake | W36: 573 | X36: 1221 | Y36: 2 | Z36: 976.8 | AA36: 3671398866 | AB36: 3671398866 | AC36: 10 | AE36: Landline | AF36: Landline | AG36: 3671398866
A37: Karnataka | B37: Visakhapatnam | C37: Men | D37: Skirts | E37: 26 | F37: 438930 | G37: Rented | H37: 45073 | I37: 1200 | J37: Earl Smith | K37: M81 | L37: USS Schmidt FPO AA 37017 | M37: 5025978956 | N37: 9 AM - 8 PM | O37: 18 | P37: Not Available | Q37: CCTV, Alarm | R37: 16135 | S37: 45482 | T37: July | U37: 444463 | V37: Wayne Jones | W37: 979 | X37: 1186 | Y37: 2 | Z37: 948.8 | AA37: 5025978956 | AB37: 5025978956 | AC37: 10 | AE37: Landline | AF37: Landline | AG37: 5025978956
A38: Karnataka | B38: Chhattisgarh | C38: Kids | D38: Pants | E38: 85 | F38: 403036 | G38: Rented | H38: 44475 | I38: 1200 | J38: Mario Romero | K38: M51 | L38: 0916 Davis Junction Apt. 169 Gonzalezberg, UT 75723 | M38: 5173065894 | N38: 9 AM - 8 PM | O38: 14 | P38: Not Available | Q38: Alarm | R38: 43510 | S38: 45494 | T38: July | U38: 535286 | V38: Ashley Serrano | W38: 336 | X38: 2865 | Y38: 6 | Z38: 6876 | AA38: 5173065894 | AB38: 5173065894 | AC38: 10 | AE38: Landline | AF38: Landline | AG38: 5173065894
A39: Maharashtra | B39: Bhopal | C39: Men | D39: Jeans | E39: 91 | F39: 409006 | G39: Rented | H39: 45280 | I39: 1300 | J39: Randy Woods | K39: M49 | L39: 969 John Turnpike Apt. 786 North Guy, MT 77498 | M39: 1151681262 | N39: 10 AM - 7 PM | O39: 14 | P39: Not Available | Q39: CCTV | R39: 75932 | S39: 45357 | T39: March | U39: 940270 | V39: Beth Harris | W39: 687 | X39: 2338 | Y39: 5 | Z39: 4676 | AA39: 1151681262 | AB39: 1151681262 | AC39: 10 | AE39: Landline | AF39: Landline | AG39: 1151681262
A40: Delhi | B40: Solapur | C40: Men | D40: Jackets | E40: 38 | F40: 401962 | G40: Owned | H40: 44837 | I40: 950 | J40: Mr. Aaron Campbell | K40: M90 | L40: 040 Clark Underpass New Juliemouth, CA 77422 | M40: 2415947152 | N40: 10 AM - 7 PM | O40: 3 | P40: Not Available | Q40: CCTV, Alarm | R40: 23907 | S40: 45612 | T40: November | U40: 908509 | V40: Jessica Wade | W40: 414 | X40: 2961 | Y40: 2 | Z40: 2368.8 | AA40: 2415947152 | AB40: 2415947152 | AC40: 10 | AE40: Landline | AF40: Landline | AG40: 2415947152
A41: Delhi | B41: Solapur | C41: Women | D41: Shirts | E41: 30 | F41: 419755 | G41: Rented | H41: 44080 | I41: 800 | J41: Richard Peterson | K41: M5 | L41: 293 Allen Valleys West Michael, RI 63572 | M41: 15910039759 | N41: 9 AM - 8 PM | O41: 6 | P41: Available | Q41: CCTV, Alarm | R41: 25187 | S41: 45578 | T41: October | U41: 941898 | V41: Christopher Beltran | W41: 320 | X41: 2581 | Y41: 1 | Z41: 1032.4 | AA41: 15910039759 | AB41: 15910039759 | AC41: 11 | AE41: Landline | AF41: Landline | AG41: 15910039759
A42: Maharashtra | B42: Kanpur | C42: Kids | D42: Shoes | E42: 29 | F42: 431080 | G42: Rented | H42: 44622 | I42: 1100 | J42: Anthony Lopez | K42: M41 | L42: USS Thomas FPO AP 73808 | M42: 2142511230 | N42: 11 AM - 8 PM | O42: 8 | P42: Available | Q42: CCTV | R42: 56814 | S42: 45501 | T42: July | U42: 432990 | V42: Jay Robinson | W42: 933 | X42: 2871 | Y42: 3 | Z42: 3445.2 | AA42: 2142511230 | AB42: 2142511230 | AC42: 10 | AE42: Landline | AF42: Landline | AG42: 2142511230
A43: West Bengal | B43: Coimbatore | C43: Men | D43: Shoes | E43: 39 | F43: 438351 | G43: Owned | H43: 45080 | I43: 1300 | J43: Carla White | K43: M35 | L43: 308 Elizabeth Forges West Jamesville, MO 74432 | M43: 7871694763 | N43: 9 AM - 8 PM | O43: 9 | P43: Not Available | Q43: CCTV, Alarm | R43: 80019 | S43: 45605 | T43: November | U43: 788411 | V43: Kelly Barton | W43: 561 | X43: 1682 | Y43: 6 | Z43: 4036.8 | AA43: 7871694763 | AB43: 7871694763 | AC43: 10 | AD43: Mobile | AF43: Mobile | AG43: 7871694763
A44: Delhi | B44: Jaipur | C44: Kids | D44: Sweaters | E44: 81 | F44: 410199 | G44: Owned | H44: 44768 | I44: 1100 | J44: Shannon Mitchell | K44: M65 | L44: 2742 Margaret Wells Aaronborough, NV 07692 | M44: 3660595394 | N44: 11 AM - 8 PM | O44: 19 | P44: Available | Q44: Alarm | R44: 63706 | S44: 45517 | T44: August | U44: 832524 | V44: Robert Gates | W44: 321 | X44: 2423 | Y44: 4 | Z44: 3876.8 | AA44: 3660595394 | AB44: 3660595394 | AC44: 10 | AE44: Landline | AF44: Landline | AG44: 3660595394
A45: Uttar Pradesh | B45: Coimbatore | C45: Women | D45: Shoes | E45: 31 | F45: 411273 | G45: Rented | H45: 44208 | I45: 1300 | J45: Kathy Ferrell | K45: M50 | L45: 9431 Young Circle Colemantown, MD 85309 | M45: 19003909697 | N45: 11 AM - 8 PM | O45: 20 | P45: Not Available | Q45: CCTV, Alarm | R45: 95994 | S45: 45583 | T45: October | U45: 479080 | V45: Robert Barnes | W45: 252 | X45: 2175 | Y45: 1 | Z45: 870 | AA45: 19003909697 | AB45: 19003909697 | AC45: 11 | AE45: Landline | AF45: Landline | AG45: 19003909697
A46: Uttar Pradesh | B46: Bhopal | C46: Men | D46: Tops | E46: 18 | F46: 439167 | G46: Owned | H46: 44911 | I46: 1300 | J46: Sarah Berry | K46: M84 | L46: 6768 Thompson Isle Apt. 395 Jacquelineburgh, NM 62409 | M46: 3955843877 | N46: 10 AM - 9 PM | O46: 10 | P46: Not Available | Q46: CCTV | R46: 89215 | S46: 45386 | T46: April | U46: 302553 | V46: Steven Dickson | W46: 210 | X46: 1514 | Y46: 6 | Z46: 3633.6 | AA46: 3955843877 | AB46: 3955843877 | AC46: 10 | AE46: Landline | AF46: Landline | AG46: 3955843877
A47: Uttar Pradesh | B47: Coimbatore | C47: Women | D47: Dresses | E47: 7 | F47: 401978 | G47: Owned | H47: 45368 | I47: 1200 | J47: Jessica Jones | K47: M50 | L47: 57794 Pugh Drive Suite 816 Lake Grace, MI 15499 | M47: 8589363434 | N47: 10 AM - 9 PM | O47: 8 | P47: Available | Q47: Alarm | R47: 62797 | S47: 45564 | T47: September | U47: 136009 | V47: Susan Keller | W47: 731 | X47: 2068 | Y47: 1 | Z47: 827.2 | AA47: 8589363434 | AB47: 8589363434 | AC47: 10 | AD47: Mobile | AF47: Mobile | AG47: 8589363434
A48: Gujarat | B48: Visakhapatnam | C48: Kids | D48: Shoes | E48: 82 | F48: 428780 | G48: Rented | H48: 45371 | I48: 1200 | J48: Jon Adams DDS | K48: M86 | L48: 14158 Diaz Isle Apt. 786 South Phillipfurt, UT 51624 | M48: 4647089403 | N48: 9 AM - 8 PM | O48: 13 | P48: Available | Q48: Alarm | R48: 53704 | S48: 45324 | T48: February | U48: 394771 | V48: Mindy Barry | W48: 961 | X48: 2090 | Y48: 5 | Z48: 4180 | AA48: 4647089403 | AB48: 4647089403 | AC48: 10 | AE48: Landline | AF48: Landline | AG48: 4647089403
A49: West Bengal | B49: Surat | C49: Women | D49: Pants | E49: 93 | F49: 409475 | G49: Owned | H49: 45315 | I49: 1200 | J49: Michael Klein | K49: M28 | L49: 05371 Chaney Motorway Jenniferborough, AL 95765 | M49: 0580808609 | N49: 9 AM - 8 PM | O49: 15 | P49: Available | Q49: CCTV | R49: 60531 | S49: 45484 | T49: July | U49: 214225 | V49: Elizabeth West | W49: 441 | X49: 2125 | Y49: 8 | Z49: 6800 | AA49: 0580808609 | AB49: 0580808609 | AC49: 10 | AE49: Landline | AF49: Landline | AG49: 0580808609
A50: Rajasthan | B50: Meerut | C50: Kids | D50: Shoes | E50: 18 | F50: 434381 | G50: Rented | H50: 44183 | I50: 1200 | J50: Veronica Cuevas | K50: M80 | L50: 11621 Amanda Glens Apt. 890 West Zacharyton, VT 79178 | M50: 0254062886 | N50: 10 AM - 9 PM | O50: 11 | P50: Not Available | Q50: CCTV, Alarm | R50: 53821 | S50: 45405 | T50: April | U50: 991450 | V50: Brenda Sanford | W50: 398 | X50: 1654 | Y50: 3 | Z50: 1984.8 | AA50: 0254062886 | AB50: 0254062886 | AC50: 10 | AE50: Landline | AF50: Landline | AG50: 0254062886
A51: Delhi | B51: Ranchi | C51: Women | D51: Hoodies | E51: 9 | F51: 415408 | G51: Owned | H51: 44693 | I51: 800 | J51: Eric Johnson | K51: M2 | L51: 0854 Vance Street Suite 554 East Jessicaville, DE 58351 | M51: 4541064783 | N51: 11 AM - 8 PM | O51: 6 | P51: Available | Q51: Alarm | R51: 80369 | S51: 45352 | T51: March | U51: 849048 | V51: Garrett Erickson | W51: 915 | X51: 1245 | Y51: 6 | Z51: 2988 | AA51: 4541064783 | AB51: 4541064783 | AC51: 10 | AE51: Landline | AF51: Landline | AG51: 4541064783
A52: Gujarat | B52: Surat | C52: Kids | D52: Sweaters | E52: 7 | F52: 426430 | G52: Owned | H52: 45082 | I52: 1300 | J52: Tammy Martinez | K52: M91 | L52: 57812 Rhonda Stream Suite 602 New Daniel, SC 99084 | M52: 9933662107 | N52: 10 AM - 9 PM | O52: 6 | P52: Not Available | Q52: None | R52: 59759 | S52: 45296 | T52: January | U52: 438133 | V52: Jennifer Blanchard | W52: 515 | X52: 1889 | Y52: 6 | Z52: 4533.6 | AA52: 9933662107 | AB52: 9933662107 | AC52: 10 | AD52: Mobile | AF52: Mobile | AG52: 9933662107
A53: Delhi | B53: Agra | C53: Kids | D53: Skirts | E53: 64 | F53: 418175 | G53: Rented | H53: 44562 | I53: 1400 | J53: Cindy Johnson DDS | K53: M82 | L53: 48650 Gregory Meadows Josephside, TN 64075 | M53: 3289125273 | N53: 9 AM - 8 PM | O53: 8 | P53: Available | Q53: CCTV, Alarm | R53: 80997 | S53: 45561 | T53: September | U53: 927589 | V53: Andrea Figueroa | W53: 272 | X53: 1487 | Y53: 7 | Z53: 4163.6 | AA53: 3289125273 | AB53: 3289125273 | AC53: 10 | AE53: Landline | AF53: Landline | AG53: 3289125273
A54: Gujarat | B54: Kolhapur | C54: Kids | D54: Dresses | E54: 9 | F54: 409835 | G54: Owned | H54: 44923 | I54: 1000 | J54: Brett Hernandez | K54: M33 | L54: 108 Sharp Springs Apt. 830 Kathrynmouth, OK 86321 | M54: 7976094654 | N54: 10 AM - 7 PM | O54: 8 | P54: Available | Q54: None | R54: 75091 | S54: 45550 | T54: September | U54: 983510 | V54: Anne Smith | W54: 416 | X54: 2100 | Y54: 6 | Z54: 5040 | AA54: 7976094654 | AB54: 7976094654 | AC54: 10 | AD54: Mobile | AF54: Mobile | AG54: 7976094654
A55: Delhi | B55: Chandigarh | C55: Women | D55: Tops | E55: 13 | F55: 407263 | G55: Rented | H55: 44834 | I55: 1000 | J55: Anthony Arias | K55: M91 | L55: USS Hale FPO AP 96253 | M55: 2899718631 | N55: 9 AM - 8 PM | O55: 6 | P55: Not Available | Q55: None | R55: 38599 | S55: 45431 | T55: May | U55: 191752 | V55: Benjamin Spence | W55: 955 | X55: 1250 | Y55: 4 | Z55: 2000 | AA55: 2899718631 | AB55: 2899718631 | AC55: 10 | AE55: Landline | AF55: Landline | AG55: 2899718631
A56: Karnataka | B56: Mysuru | C56: Women | D56: Skirts | E56: 90 | F56: 429912 | G56: Rented | H56: 45317 | I56: 800 | J56: Stephanie Montgomery | K56: M10 | L56: 693 Parks Flats Dudleyville, MI 82485 | M56: 5853852302 | N56: 10 AM - 9 PM | O56: 15 | P56: Not Available | Q56: CCTV, Alarm | R56: 10561 | S56: 45569 | T56: October | U56: 891651 | V56: Matthew Barron | W56: 463 | X56: 1780 | Y56: 3 | Z56: 2136 | AA56: 5853852302 | AB56: 5853852302 | AC56: 10 | AE56: Landline | AF56: Landline | AG56: 5853852302
A57: Delhi | B57: Pune | C57: Kids | D57: Shoes | E57: 36 | F57: 421312 | G57: Owned | H57: 44265 | I57: 950 | J57: Valerie Garner | K57: M96 | L57: USS Kennedy FPO AE 78632 | M57: 5194071882 | N57: 10 AM - 7 PM | O57: 13 | P57: Not Available | Q57: None | R57: 76855 | S57: 45551 | T57: September | U57: 628181 | V57: Tracey Flores | W57: 982 | X57: 1812 | Y57: 8 | Z57: 5798.4 | AA57: 5194071882 | AB57: 5194071882 | AC57: 10 | AE57: Landline | AF57: Landline | AG57: 5194071882
A58: West Bengal | B58: Ranchi | C58: Kids | D58: Pants | E58: 19 | F58: 429962 | G58: Owned | H58: 45105 | I58: 1100 | J58: Timothy Porter | K58: M85 | L58: 193 Ross Hill Apt. 335 West Kimberly, CT 43628 | M58: 17349385620 | N58: 10 AM - 9 PM | O58: 18 | P58: Not Available | Q58: CCTV, Alarm | R58: 58524 | S58: 45383 | T58: April | U58: 412344 | V58: Diane Fischer | W58: 299 | X58: 2223 | Y58: 8 | Z58: 7113.6 | AA58: 17349385620 | AB58: 17349385620 | AC58: 11 | AE58: Landline | AF58: Landline | AG58: 17349385620
A59: Maharashtra | B59: Kochi | C59: Men | D59: Sweaters | E59: 81 | F59: 439476 | G59: Owned | H59: 45022 | I59: 1300 | J59: Tammy Robinson | K59: M87 | L59: 92307 Lin Curve Lake Jeffrey, PA 24825 | M59: 5671861596 | N59: 10 AM - 7 PM | O59: 18 | P59: Available | Q59: CCTV, Alarm | R59: 13902 | S59: 45439 | T59: May | U59: 560848 | V59: Dustin Freeman | W59: 511 | X59: 2994 | Y59: 4 | Z59: 4790.4 | AA59: 5671861596 | AB59: 5671861596 | AC59: 10 | AE59: Landline | AF59: Landline | AG59: 5671861596
A60: Karnataka | B60: Coimbatore | C60: Women | D60: Shirts | E60: 78 | F60: 425488 | G60: Rented | H60: 45103 | I60: 800 | J60: Vanessa Black | K60: M49 | L60: 396 James Shores West Haley, ND 67486 | M60: 1428508596 | N60: 9 AM - 8 PM | O60: 18 | P60: Not Available | Q60: CCTV, Alarm | R60: 19993 | S60: 45620 | T60: November | U60: 300708 | V60: Douglas Martinez | W60: 338 | X60: 2564 | Y60: 6 | Z60: 6153.6 | AA60: 1428508596 | AB60: 1428508596 | AC60: 10 | AE60: Landline | AF60: Landline | AG60: 1428508596
A61: Rajasthan | B61: Kolhapur | C61: Kids | D61: Dresses | E61: 19 | F61: 423849 | G61: Rented | H61: 44476 | I61: 950 | J61: Derek Davis | K61: M26 | L61: 5800 Regina Corner Port Jillmouth, PA 04821 | M61: 4551239312 | N61: 10 AM - 7 PM | O61: 15 | P61: Available | Q61: CCTV | R61: 53480 | S61: 45444 | T61: June | U61: 352227 | V61: John Coleman | W61: 777 | X61: 1763 | Y61: 4 | Z61: 2820.8 | AA61: 4551239312 | AB61: 4551239312 | AC61: 10 | AE61: Landline | AF61: Landline | AG61: 4551239312
A62: Gujarat | B62: Mysuru | C62: Women | D62: T-Shirts | E62: 10 | F62: 408582 | G62: Owned | H62: 44393 | I62: 1200 | J62: Stacey Washington | K62: M92 | L62: 60503 Nicholas Valleys Lake Troy, NE 36238 | M62: 9626345208 | N62: 10 AM - 9 PM | O62: 14 | P62: Available | Q62: CCTV | R62: 43865 | S62: 45562 | T62: September | U62: 215122 | V62: Holly Woodward | W62: 596 | X62: 698 | Y62: 5 | Z62: 1396 | AA62: 9626345208 | AB62: 9626345208 | AC62: 10 | AD62: Mobile | AF62: Mobile | AG62: 9626345208
A63: Rajasthan | B63: Meerut | C63: Men | D63: Jeans | E63: 65 | F63: 427663 | G63: Rented | H63: 45127 | I63: 950 | J63: Robert Vargas | K63: M52 | L63: 35241 Richards Falls Suite 048 Leslieview, TN 76719 | M63: 3331712106 | N63: 10 AM - 7 PM | O63: 4 | P63: Available | Q63: None | R63: 14830 | S63: 45396 | T63: April | U63: 529349 | V63: John Calhoun | W63: 330 | X63: 1813 | Y63: 2 | Z63: 1450.4 | AA63: 3331712106 | AB63: 3331712106 | AC63: 10 | AE63: Landline | AF63: Landline | AG63: 3331712106
A64: Maharashtra | B64: Kanpur | C64: Women | D64: Jackets | E64: 11 | F64: 426493 | G64: Rented | H64: 44983 | I64: 950 | J64: Michaela Martinez | K64: M56 | L64: 12921 Freeman Tunnel Apt. 678 Nunezmouth, ID 93663 | M64: 1151917336 | N64: 11 AM - 8 PM | O64: 12 | P64: Available | Q64: CCTV | R64: 12454 | S64: 45367 | T64: March | U64: 538513 | V64: Terry Williams | W64: 942 | X64: 2141 | Y64: 1 | Z64: 856.4 | AA64: 1151917336 | AB64: 1151917336 | AC64: 10 | AE64: Landline | AF64: Landline | AG64: 1151917336
A65: Karnataka | B65: Chhattisgarh | C65: Men | D65: Hoodies | E65: 52 | F65: 418048 | G65: Owned | H65: 45439 | I65: 1400 | J65: Jeremy Cox | K65: M34 | L65: 786 Curtis Springs East Ericaport, MT 76364 | M65: 5485515899 | N65: 10 AM - 7 PM | O65: 15 | P65: Available | Q65: CCTV, Alarm | R65: 60292 | S65: 45381 | T65: March | U65: 914885 | V65: Robin Buckley | W65: 983 | X65: 1399 | Y65: 4 | Z65: 2238.4 | AA65: 5485515899 | AB65: 5485515899 | AC65: 10 | AE65: Landline | AF65: Landline | AG65: 5485515899
A66: Tamil Nadu | B66: Ranchi | C66: Men | D66: Hoodies | E66: 73 | F66: 437308 | G66: Rented | H66: 45092 | I66: 1000 | J66: Jason Brown | K66: M15 | L66: 492 Jacqueline Shores South Rebekah, TX 87189 | M66: 7412903648 | N66: 9 AM - 8 PM | O66: 8 | P66: Available | Q66: CCTV, Alarm | R66: 38238 | S66: 45525 | T66: August | U66: 380177 | V66: Lisa Sanders | W66: 856 | X66: 1143 | Y66: 3 | Z66: 1371.6 | AA66: 7412903648 | AB66: 7412903648 | AC66: 10 | AD66: Mobile | AF66: Mobile | AG66: 7412903648
A67: Delhi | B67: Vadodara | C67: Kids | D67: Shoes | E67: 93 | F67: 434410 | G67: Rented | H67: 44575 | I67: 1000 | J67: George Weiss | K67: M61 | L67: 74200 Blevins Viaduct Farmermouth, ME 85957 | M67: 6927099373 | N67: 10 AM - 7 PM | O67: 18 | P67: Available | Q67: None | R67: 45645 | S67: 45443 | T67: May | U67: 813930 | V67: Zachary Miles | W67: 295 | X67: 2261 | Y67: 1 | Z67: 904.4 | AA67: 6927099373 | AB67: 6927099373 | AC67: 10 | AD67: Mobile | AF67: Mobile | AG67: 6927099373
A68: Gujarat | B68: Ahmedabad | C68: Men | D68: Skirts | E68: 17 | F68: 404804 | G68: Rented | H68: 44989 | I68: 1200 | J68: Julie Thomas | K68: M21 | L68: 62228 Jane Route East Lori, OR 29041 | M68: 14636712351 | N68: 10 AM - 7 PM | O68: 9 | P68: Available | Q68: None | R68: 91097 | S68: 45398 | T68: April | U68: 980069 | V68: Charles Huerta | W68: 392 | X68: 2907 | Y68: 3 | Z68: 3488.4 | AA68: 14636712351 | AB68: 14636712351 | AC68: 11 | AE68: Landline | AF68: Landline | AG68: 14636712351
A69: Tamil Nadu | B69: Kanpur | C69: Men | D69: Shoes | E69: 53 | F69: 409354 | G69: Rented | H69: 44641 | I69: 1200 | J69: Kimberly Cooper | K69: M68 | L69: 8342 Shaw Harbors Apt. 019 South Kathryn, FL 22461 | M69: 9958859895 | N69: 10 AM - 9 PM | O69: 13 | P69: Not Available | Q69: None | R69: 40055 | S69: 45377 | T69: March | U69: 677047 | V69: Sharon Patel | W69: 294 | X69: 1640 | Y69: 5 | Z69: 3280 | AA69: 9958859895 | AB69: 9958859895 | AC69: 10 | AD69: Mobile | AF69: Mobile | AG69: 9958859895
A70: Rajasthan | B70: Indore | C70: Kids | D70: Tops | E70: 27 | F70: 422503 | G70: Owned | H70: 45245 | I70: 800 | J70: Jason Carey DDS | K70: M8 | L70: 45069 Nicholas Extension Suite 290 Austinton, MT 37379 | M70: 1428395239 | N70: 10 AM - 7 PM | O70: 12 | P70: Available | Q70: None | R70: 47432 | S70: 45550 | T70: September | U70: 278951 | V70: Susan Murphy | W70: 627 | X70: 1929 | Y70: 7 | Z70: 5401.2 | AA70: 1428395239 | AB70: 1428395239 | AC70: 10 | AE70: Landline | AF70: Landline | AG70: 1428395239
A71: Gujarat | B71: Goa | C71: Women | D71: Hoodies | E71: 15 | F71: 429557 | G71: Owned | H71: 44054 | I71: 1000 | J71: Michael Edwards | K71: M36 | L71: 4074 Powell Corners Apt. 012 Brittanymouth, NJ 55927 | M71: 6140652581 | N71: 11 AM - 8 PM | O71: 7 | P71: Not Available | Q71: None | R71: 88876 | S71: 45594 | T71: October | U71: 886198 | V71: John Sexton | W71: 565 | X71: 1557 | Y71: 6 | Z71: 3736.8 | AA71: 6140652581 | AB71: 6140652581 | AC71: 10 | AD71: Mobile | AF71: Mobile | AG71: 6140652581
A72: Uttar Pradesh | B72: Chandigarh | C72: Women | D72: Shoes | E72: 60 | F72: 422917 | G72: Owned | H72: 45431 | I72: 1000 | J72: Judith White | K72: M59 | L72: 581 Potts Ranch South Karenland, HI 49683 | M72: 0370454522 | N72: 10 AM - 9 PM | O72: 13 | P72: Available | Q72: CCTV, Alarm | R72: 65887 | S72: 45501 | T72: July | U72: 840385 | V72: Shaun Ferguson | W72: 410 | X72: 2805 | Y72: 2 | Z72: 2244 | AA72: 0370454522 | AB72: 0370454522 | AC72: 10 | AE72: Landline | AF72: Landline | AG72: 0370454522
A73: Rajasthan | B73: Mysuru | C73: Men | D73: Tops | E73: 27 | F73: 410113 | G73: Rented | H73: 45325 | I73: 1300 | J73: Kevin Frost | K73: M36 | L73: 367 Adams Stravenue Lake Amandamouth, VT 54367 | M73: 7189520269 | N73: 10 AM - 7 PM | O73: 3 | P73: Available | Q73: None | R73: 72581 | S73: 45566 | T73: October | U73: 402475 | V73: Robin Burns | W73: 349 | X73: 2441 | Y73: 7 | Z73: 6834.8 | AA73: 7189520269 | AB73: 7189520269 | AC73: 10 | AD73: Mobile | AF73: Mobile | AG73: 7189520269
A74: Delhi | B74: Lucknow | C74: Men | D74: Tops | E74: 60 | F74: 421192 | G74: Owned | H74: 45176 | I74: 1000 | J74: Nathaniel Harrison | K74: M22 | L74: USNS Wilkins FPO AE 03351 | M74: 5979593984 | N74: 10 AM - 7 PM | O74: 7 | P74: Available | Q74: CCTV, Alarm | R74: 69923 | S74: 45341 | T74: February | U74: 955782 | V74: Kathleen Lee | W74: 247 | X74: 1460 | Y74: 7 | Z74: 4088 | AA74: 5979593984 | AB74: 5979593984 | AC74: 10 | AE74: Landline | AF74: Landline | AG74: 5979593984
A75: Tamil Nadu | B75: Kolhapur | C75: Women | D75: Shirts | E75: 94 | F75: 428968 | G75: Rented | H75: 45141 | I75: 1000 | J75: Rachel Dalton | K75: M55 | L75: 352 Kristopher Overpass Suite 677 West Stephanieside, TN 35808 | M75: 7621293523 | N75: 10 AM - 7 PM | O75: 20 | P75: Not Available | Q75: None | R75: 88966 | S75: 45454 | T75: June | U75: 311954 | V75: Michelle Nguyen | W75: 270 | X75: 1825 | Y75: 6 | Z75: 4380 | AA75: 7621293523 | AB75: 7621293523 | AC75: 10 | AD75: Mobile | AF75: Mobile | AG75: 7621293523
A76: Maharashtra | B76: Rajkot | C76: Women | D76: Shirts | E76: 80 | F76: 428249 | G76: Rented | H76: 44078 | I76: 1400 | J76: Corey Savage | K76: M8 | L76: Unit 0847 Box 8298 DPO AP 69852 | M76: 3668633365 | N76: 10 AM - 7 PM | O76: 14 | P76: Available | Q76: CCTV | R76: 15079 | S76: 45352 | T76: March | U76: 533468 | V76: Colleen Tate | W76: 548 | X76: 2346 | Y76: 2 | Z76: 1876.8 | AA76: 3668633365 | AB76: 3668633365 | AC76: 10 | AE76: Landline | AF76: Landline | AG76: 3668633365
A77: Gujarat | B77: Mumbai | C77: Kids | D77: Jeans | E77: 84 | F77: 419932 | G77: Rented | H77: 44148 | I77: 1100 | J77: Amanda Spence | K77: M91 | L77: 3627 Omar Views Apt. 203 Port Matthewstad, FL 50234 | M77: 3001497552 | N77: 11 AM - 8 PM | O77: 14 | P77: Available | Q77: Alarm | R77: 11636 | S77: 45495 | T77: July | U77: 166274 | V77: Yvette Obrien | W77: 676 | X77: 998 | Y77: 2 | Z77: 798.4 | AA77: 3001497552 | AB77: 3001497552 | AC77: 10 | AE77: Landline | AF77: Landline | AG77: 3001497552
A78: Delhi | B78: Jaipur | C78: Men | D78: Shirts | E78: 4 | F78: 439376 | G78: Owned | H78: 45194 | I78: 1400 | J78: Lisa Miles | K78: M4 | L78: 779 Sims Village West Katherineview, AZ 12981 | M78: 6164010102 | N78: 11 AM - 8 PM | O78: 10 | P78: Not Available | Q78: Alarm | R78: 74975 | S78: 45384 | T78: April | U78: 499296 | V78: Ronald Zamora | W78: 356 | X78: 1767 | Y78: 4 | Z78: 2827.2 | AA78: 6164010102 | AB78: 6164010102 | AC78: 10 | AD78: Mobile | AF78: Mobile | AG78: 6164010102
A79: West Bengal | B79: Coimbatore | C79: Kids | D79: Shoes | E79: 41 | F79: 409570 | G79: Owned | H79: 44053 | I79: 800 | J79: Amy Ware | K79: M42 | L79: 2134 Matthews Canyon Suite 880 Nicholasland, SD 43899 | M79: 1379715618 | N79: 10 AM - 9 PM | O79: 9 | P79: Not Available | Q79: CCTV | R79: 70721 | S79: 45325 | T79: February | U79: 445491 | V79: Nichole Williams | W79: 733 | X79: 861 | Y79: 5 | Z79: 1722 | AA79: 1379715618 | AB79: 1379715618 | AC79: 10 | AE79: Landline | AF79: Landline | AG79: 1379715618
A80: Rajasthan | B80: Nashik | C80: Kids | D80: Tops | E80: 97 | F80: 407331 | G80: Rented | H80: 45320 | I80: 1400 | J80: Mr. Jacob Miles | K80: M95 | L80: 6479 Christine Mountains Perezchester, AZ 35887 | M80: 6621983194 | N80: 10 AM - 7 PM | O80: 4 | P80: Not Available | Q80: CCTV, Alarm | R80: 35297 | S80: 45292 | T80: January | U80: 237215 | V80: Erica Hughes | W80: 459 | X80: 1200 | Y80: 1 | Z80: 480 | AA80: 6621983194 | AB80: 6621983194 | AC80: 10 | AD80: Mobile | AF80: Mobile | AG80: 6621983194
A81: Rajasthan | B81: Pune | C81: Women | D81: Shirts | E81: 63 | F81: 429638 | G81: Rented | H81: 44397 | I81: 1200 | J81: Mark Allen | K81: M62 | L81: 7988 Walsh Common Apt. 336 Jasonshire, WI 06415 | M81: 2581462567 | N81: 9 AM - 8 PM | O81: 11 | P81: Available | Q81: None | R81: 28416 | S81: 45456 | T81: June | U81: 811058 | V81: Devin Dillon | W81: 338 | X81: 1332 | Y81: 8 | Z81: 4262.4 | AA81: 2581462567 | AB81: 2581462567 | AC81: 10 | AE81: Landline | AF81: Landline | AG81: 2581462567
A82: Uttar Pradesh | B82: Agra | C82: Men | D82: Shirts | E82: 19 | F82: 406436 | G82: Rented | H82: 45371 | I82: 1300 | J82: Peter Eaton | K82: M71 | L82: Unit 9188 Box 1212 DPO AE 45339 | M82: 9670204374 | N82: 10 AM - 9 PM | O82: 13 | P82: Available | Q82: CCTV | R82: 42774 | S82: 45315 | T82: January | U82: 859669 | V82: Joshua Sanders | W82: 395 | X82: 2354 | Y82: 4 | Z82: 3766.4 | AA82: 9670204374 | AB82: 9670204374 | AC82: 10 | AD82: Mobile | AF82: Mobile | AG82: 9670204374
A83: West Bengal | B83: Rajkot | C83: Kids | D83: Jackets | E83: 99 | F83: 432808 | G83: Rented | H83: 44327 | I83: 1200 | J83: Erin Lopez | K83: M27 | L83: 23078 Walsh Skyway Suite 836 Rhodestown, MS 65221 | M83: 6154779431 | N83: 9 AM - 8 PM | O83: 17 | P83: Not Available | Q83: Alarm | R83: 62910 | S83: 45329 | T83: February | U83: 686506 | V83: Matthew Lee | W83: 253 | X83: 2667 | Y83: 5 | Z83: 5334 | AA83: 6154779431 | AB83: 6154779431 | AC83: 10 | AD83: Mobile | AF83: Mobile | AG83: 6154779431
A84: Maharashtra | B84: Mumbai | C84: Women | D84: Shirts | E84: 18 | F84: 410593 | G84: Rented | H84: 44284 | I84: 1200 | J84: Matthew Rangel | K84: M57 | L84: 676 Leslie Inlet Apt. 140 Carrilloview, GA 13055 | M84: 12948799701 | N84: 10 AM - 9 PM | O84: 6 | P84: Available | Q84: CCTV | R84: 48886 | S84: 45520 | T84: August | U84: 994056 | V84: Rachael Garza | W84: 384 | X84: 2433 | Y84: 4 | Z84: 3892.8 | AA84: 12948799701 | AB84: 12948799701 | AC84: 11 | AE84: Landline | AF84: Landline | AG84: 12948799701
A85: Rajasthan | B85: Chandigarh | C85: Kids | D85: Jeans | E85: 84 | F85: 401657 | G85: Owned | H85: 43919 | I85: 800 | J85: Kelly Warren | K85: M62 | L85: 15755 Fields Divide New Michaelville, VA 72119 | M85: 1253516857 | N85: 10 AM - 7 PM | O85: 10 | P85: Available | Q85: Alarm | R85: 45050 | S85: 45392 | T85: April | U85: 730083 | V85: Deborah Williams | W85: 780 | X85: 1185 | Y85: 2 | Z85: 948 | AA85: 1253516857 | AB85: 1253516857 | AC85: 10 | AE85: Landline | AF85: Landline | AG85: 1253516857
A86: Karnataka | B86: Surat | C86: Women | D86: Jackets | E86: 68 | F86: 408163 | G86: Rented | H86: 44564 | I86: 1100 | J86: Linda Smith | K86: M73 | L86: 858 Walker Street Suite 593 North Rebeccatown, NE 36077 | M86: 2664333141 | N86: 10 AM - 7 PM | O86: 6 | P86: Not Available | Q86: Alarm | R86: 10931 | S86: 45505 | T86: August | U86: 319571 | V86: Richard Santos | W86: 261 | X86: 1682 | Y86: 6 | Z86: 4036.8 | AA86: 2664333141 | AB86: 2664333141 | AC86: 10 | AE86: Landline | AF86: Landline | AG86: 2664333141
A87: Uttar Pradesh | B87: Mumbai | C87: Men | D87: Shirts | E87: 68 | F87: 439416 | G87: Rented | H87: 44114 | I87: 1000 | J87: Andrea Ramirez | K87: M15 | L87: 293 Knight Ford Suite 842 South Sarah, MD 39896 | M87: 5783040950 | N87: 10 AM - 9 PM | O87: 9 | P87: Available | Q87: None | R87: 89654 | S87: 45579 | T87: October | U87: 382371 | V87: Julia Pearson | W87: 585 | X87: 1185 | Y87: 1 | Z87: 474 | AA87: 5783040950 | AB87: 5783040950 | AC87: 10 | AE87: Landline | AF87: Landline | AG87: 5783040950
A88: Uttar Pradesh | B88: Bhopal | C88: Women | D88: Jackets | E88: 27 | F88: 403603 | G88: Owned | H88: 44769 | I88: 1000 | J88: Anthony Powell | K88: M99 | L88: 4737 Mayer Streets West Caitlinton, HI 38451 | M88: 16585723885 | N88: 10 AM - 7 PM | O88: 8 | P88: Not Available | Q88: CCTV | R88: 56917 | S88: 45340 | T88: February | U88: 103918 | V88: Brittany King | W88: 349 | X88: 1001 | Y88: 2 | Z88: 800.8 | AA88: 16585723885 | AB88: 16585723885 | AC88: 11 | AE88: Landline | AF88: Landline | AG88: 16585723885
A89: West Bengal | B89: Satara | C89: Women | D89: Pants | E89: 19 | F89: 439870 | G89: Owned | H89: 44617 | I89: 950 | J89: David Lawrence | K89: M69 | L89: 289 Courtney Cliffs Lake Jacob, CT 45788 | M89: 5791026605 | N89: 9 AM - 8 PM | O89: 6 | P89: Available | Q89: CCTV | R89: 34036 | S89: 45510 | T89: August | U89: 990826 | V89: Stacy York | W89: 844 | X89: 1859 | Y89: 3 | Z89: 2230.8 | AA89: 5791026605 | AB89: 5791026605 | AC89: 10 | AE89: Landline | AF89: Landline | AG89: 5791026605
A90: Delhi | B90: Visakhapatnam | C90: Men | D90: Jeans | E90: 62 | F90: 415242 | G90: Owned | H90: 44536 | I90: 1400 | J90: Monique Parrish | K90: M51 | L90: 8034 Cynthia Flats Reneemouth, NJ 44026 | M90: 6727400003 | N90: 11 AM - 8 PM | O90: 9 | P90: Not Available | Q90: None | R90: 31634 | S90: 45342 | T90: February | U90: 605668 | V90: Andrew Cox | W90: 998 | X90: 2256 | Y90: 4 | Z90: 3609.6 | AA90: 6727400003 | AB90: 6727400003 | AC90: 10 | AD90: Mobile | AF90: Mobile | AG90: 6727400003
A91: Uttar Pradesh | B91: Solapur | C91: Women | D91: T-Shirts | E91: 78 | F91: 411128 | G91: Rented | H91: 44157 | I91: 1400 | J91: Michael Richardson | K91: M33 | L91: 524 Macdonald Station Lake Ernest, OR 22420 | M91: 13417695353 | N91: 10 AM - 9 PM | O91: 11 | P91: Not Available | Q91: None | R91: 79302 | S91: 45439 | T91: May | U91: 843071 | V91: Tina Collins | W91: 216 | X91: 846 | Y91: 2 | Z91: 676.8 | AA91: 13417695353 | AB91: 13417695353 | AC91: 11 | AE91: Landline | AF91: Landline | AG91: 13417695353
A92: West Bengal | B92: New Delhi | C92: Men | D92: Shoes | E92: 87 | F92: 422194 | G92: Rented | H92: 44851 | I92: 1400 | J92: David Nguyen | K92: M72 | L92: 4105 Timothy Alley Suite 449 Nicolebury, NE 01307 | M92: 7884381037 | N92: 10 AM - 7 PM | O92: 20 | P92: Not Available | Q92: None | R92: 68140 | S92: 45539 | T92: September | U92: 378896 | V92: Christine Garcia | W92: 443 | X92: 2183 | Y92: 8 | Z92: 6985.6 | AA92: 7884381037 | AB92: 7884381037 | AC92: 10 | AD92: Mobile | AF92: Mobile | AG92: 7884381037
A93: West Bengal | B93: Chennai | C93: Women | D93: Shirts | E93: 50 | F93: 418166 | G93: Owned | H93: 45068 | I93: 950 | J93: Luke Gomez | K93: M63 | L93: 9312 Oconnor Way Apt. 430 Lake April, DC 26467 | M93: 7299537333 | N93: 10 AM - 7 PM | O93: 15 | P93: Not Available | Q93: CCTV | R93: 72835 | S93: 45390 | T93: April | U93: 896301 | V93: Nicole Martin | W93: 339 | X93: 2422 | Y93: 5 | Z93: 4844 | AA93: 7299537333 | AB93: 7299537333 | AC93: 10 | AD93: Mobile | AF93: Mobile | AG93: 7299537333
A94: West Bengal | B94: Chandigarh | C94: Kids | D94: Skirts | E94: 18 | F94: 412945 | G94: Owned | H94: 44240 | I94: 1200 | J94: Thomas Day | K94: M34 | L94: 235 Tony Center Buchanantown, PA 64118 | M94: 8784896986 | N94: 10 AM - 7 PM | O94: 12 | P94: Not Available | Q94: CCTV | R94: 78235 | S94: 45381 | T94: March | U94: 103287 | V94: Craig Jackson | W94: 778 | X94: 2637 | Y94: 2 | Z94: 2109.6 | AA94: 8784896986 | AB94: 8784896986 | AC94: 10 | AD94: Mobile | AF94: Mobile | AG94: 8784896986
A95: Tamil Nadu | B95: Visakhapatnam | C95: Men | D95: Sweaters | E95: 21 | F95: 410764 | G95: Rented | H95: 44317 | I95: 950 | J95: Anthony Collins | K95: M12 | L95: 2509 Norton Plaza North Anthonyfurt, GA 52382 | M95: 8364517820 | N95: 10 AM - 9 PM | O95: 7 | P95: Available | Q95: CCTV | R95: 48503 | S95: 45561 | T95: September | U95: 133260 | V95: Brittney Barton | W95: 524 | X95: 1411 | Y95: 1 | Z95: 564.4 | AA95: 8364517820 | AB95: 8364517820 | AC95: 10 | AD95: Mobile | AF95: Mobile | AG95: 8364517820
A96: Uttar Pradesh | B96: Nagpur | C96: Kids | D96: Skirts | E96: 23 | F96: 434688 | G96: Owned | H96: 44273 | I96: 800 | J96: Kenneth Castillo | K96: M66 | L96: 2537 Harper Bridge Apt. 599 Port Lauren, ME 83049 | M96: 7125876577 | N96: 10 AM - 7 PM | O96: 11 | P96: Not Available | Q96: CCTV, Alarm | R96: 85212 | S96: 45508 | T96: August | U96: 640393 | V96: Dana Lin | W96: 428 | X96: 2430 | Y96: 6 | Z96: 5832 | AA96: 7125876577 | AB96: 7125876577 | AC96: 10 | AD96: Mobile | AF96: Mobile | AG96: 7125876577
A97: Uttar Pradesh | B97: Goa | C97: Kids | D97: Pants | E97: 58 | F97: 436573 | G97: Rented | H97: 43896 | I97: 800 | J97: Shannon Watkins | K97: M81 | L97: 5341 Williams Land South Jeremyville, UT 74169 | M97: 9595451684 | N97: 11 AM - 8 PM | O97: 5 | P97: Available | Q97: CCTV | R97: 54024 | S97: 45573 | T97: October | U97: 298754 | V97: Jeffrey Harrison | W97: 564 | X97: 2250 | Y97: 8 | Z97: 7200 | AA97: 9595451684 | AB97: 9595451684 | AC97: 10 | AD97: Mobile | AF97: Mobile | AG97: 9595451684
A98: Uttar Pradesh | B98: Hyderabad | C98: Men | D98: Jackets | E98: 22 | F98: 438365 | G98: Owned | H98: 43934 | I98: 1100 | J98: Courtney Hall | K98: M44 | L98: 766 James Isle Suite 628 North Stephenshire, NV 71186 | M98: 7939100051 | N98: 9 AM - 8 PM | O98: 18 | P98: Not Available | Q98: CCTV, Alarm | R98: 50146 | S98: 45336 | T98: February | U98: 979314 | V98: Eric Lowery | W98: 732 | X98: 2444 | Y98: 6 | Z98: 5865.6 | AA98: 7939100051 | AB98: 7939100051 | AC98: 10 | AD98: Mobile | AF98: Mobile | AG98: 7939100051
A99: Maharashtra | B99: Hyderabad | C99: Men | D99: Shoes | E99: 6 | F99: 424641 | G99: Owned | H99: 44520 | I99: 950 | J99: Gregory Hancock | K99: M24 | L99: 53247 Timothy Underpass Apt. 397 Lake Jacqueline, TX 47459 | M99: 4568186081 | N99: 11 AM - 8 PM | O99: 13 | P99: Not Available | Q99: CCTV | R99: 86534 | S99: 45536 | T99: September | U99: 106875 | V99: Kristen Edwards | W99: 264 | X99: 1439 | Y99: 3 | Z99: 1726.8 | AA99: 4568186081 | AB99: 4568186081 | AC99: 10 | AE99: Landline | AF99: Landline | AG99: 4568186081
A100: Tamil Nadu | B100: Madurai | C100: Kids | D100: Jeans | E100: 85 | F100: 400802 | G100: Rented | H100: 45114 | I100: 1400 | J100: Juan Johnson | K100: M80 | L100: 49614 Mackenzie Fields Suite 469 Sanchezbury, ID 54436 | M100: 2690323397 | N100: 10 AM - 7 PM | O100: 8 | P100: Available | Q100: CCTV | R100: 37045 | S100: 45367 | T100: March | U100: 666256 | V100: Juan Jackson | W100: 355 | X100: 2516 | Y100: 7 | Z100: 7044.8 | AA100: 2690323397 | AB100: 2690323397 | AC100: 10 | AE100: Landline | AF100: Landline | AG100: 2690323397
...

Sheet kpi linechart
A3: Sum of Sales | B3: Sum of Quantity | C3: Count of Order ID | D3: AVG ORDER VALUE | E3: Distinct Count of Store Number | F3: Average of Assumed margin | G3: Sum of Sales
A4: 8842540.4 | B4: 12572 | C4: 2779 | D4: =GETPIVOTDATA("Sales",$A$3)/GETPIVOTDATA("Order ID",$C$3) -> 3181.9145 | E4: 100 | F4: 0.2824973 | G4: 8842540.4
A7: Row Labels | B7: Sum of Sales
A8: Jan
A9: 1 | B9: 791005.6
A10: Feb
A11: 2 | B11: 839878.8
A12: Mar
A13: 3 | B13: 765862.4
A14: Apr
A15: 4 | B15: 816146.8
A16: May
A17: 5 | B17: 756070.8
A18: Jun
A19: 6 | B19: 754773.2
A20: Jul
A21: 7 | B21: 790390.8
A22: Aug
A23: 8 | B23: 818040
A24: Sep
A25: 9 | B25: 686611.6
A26: Oct
A27: 10 | B27: 806040.4
A28: Nov
A29: 11 | B29: 918799.2
A30: Dec
A31: 12 | B31: 98920.8
A32: Grand Total | B32: 8842540.4

Sheet category chart
A3: Row Labels | B3: Sum of Sales
A4: Women | B4: 3018398.8
A5: Men | B5: 2954828.4
A6: Kids | B6: 2869313.2
A7: Grand Total | B7: 8842540.4

Sheet Top 10
A3: Row Labels | B3: Sum of Sales
A4: 338 | B4: 39009.2
A5: 405 | B5: 30987.2
A6: 501 | B6: 32221.6
A7: 576 | B7: 35178
A8: 584 | B8: 36420.8
A9: 597 | B9: 31285.6
A10: 632 | B10: 32167.6
A11: 652 | B11: 35679.2
A12: 738 | B12: 33326
A13: 976 | B13: 30986
A14: Grand Total | B14: 337261.2

Sheet map chart
A3: Row Labels | B3: Sum of Sales | D3: state | E3: sales
A4: Andhra Pradesh | B4: 213454 | D4: =A4 -> Andhra Pradesh | E4: =GETPIVOTDATA("[Measures].[Sum of Sales]",$A$3,"[Zudio_sales_data].[State]","[Zudio_sales_data].[State].&[Andhra Pradesh]") -> 213454
A5: Assam | B5: 211584 | D5: =A5 -> Assam | E5: =GETPIVOTDATA("[Measures].[Sum of Sales]",$A$3,"[Zudio_sales_data].[State]","[Zudio_sales_data].[State].&[Assam]") -> 211584
A6: Bihar | B6: 211697.6 | D6: =A6 -> Bihar | E6: =GETPIVOTDATA("[Measures].[Sum of Sales]",$A$3,"[Zudio_sales_data].[State]","[Zudio_sales_data].[State].&[Bihar]") -> 211697.6
A7: Chandigarh | B7: 187812.8 | D7: =A7 -> Chandigarh | E7: =GETPIVOTDATA("[Measures].[Sum of Sales]",$A$3,"[Zudio_sales_data].[State]","[Zudio_sales_data].[State].&[Chandigarh]") -> 187812.8
A8: Chhattisgarh | B8: 227924 | D8: =A8 -> Chhattisgarh | E8: =GETPIVOTDATA("[Measures].[Sum of Sales]",$A$3,"[Zudio_sales_data].[State]","[Zudio_sales_data].[State].&[Chhattisgarh]") -> 227924
A9: Delhi | B9: 228078.4 | D9: =A9 -> Delhi | E9: =GETPIVOTDATA("[Measures].[Sum of Sales]",$A$3,"[Zudio_sales_data].[State]","[Zudio_sales_data].[State].&[Delhi]") -> 228078.4
A10: Goa | B10: 203632.4 | D10: =A10 -> Goa | E10: =GETPIVOTDATA("[Measures].[Sum of Sales]",$A$3,"[Zudio_sales_data].[State]","[Zudio_sales_data].[State].&[Goa]") -> 203632.4
A11: Gujarat | B11: 921890.4 | D11: =A11 -> Gujarat | E11: =GETPIVOTDATA("[Measures].[Sum of Sales]",$A$3,"[Zudio_sales_data].[State]","[Zudio_sales_data].[State].&[Gujarat]") -> 921890.4
A12: Haryana | B12: 214726 | D12: =A12 -> Haryana | E12: =GETPIVOTDATA("[Measures].[Sum of Sales]",$A$3,"[Zudio_sales_data].[State]","[Zudio_sales_data].[State].&[Haryana]") -> 214726
A13: Jammu and Kashmir | B13: 215214.4 | D13: =A13 -> Jammu and Kashmir | E13: =GETPIVOTDATA("[Measures].[Sum of Sales]",$A$3,"[Zudio_sales_data].[State]","[Zudio_sales_data].[State].&[Jammu and Kashmir]") -> 215214.4
A14: Jharkhand | B14: 217012 | D14: =A14 -> Jharkhand | E14: =GETPIVOTDATA("[Measures].[Sum of Sales]",$A$3,"[Zudio_sales_data].[State]","[Zudio_sales_data].[State].&[Jharkhand]") -> 217012
A15: Karnataka | B15: 424235.6 | D15: =A15 -> Karnataka | E15: =GETPIVOTDATA("[Measures].[Sum of Sales]",$A$3,"[Zudio_sales_data].[State]","[Zudio_sales_data].[State].&[Karnataka]") -> 424235.6
A16: Kerala | B16: 172963.6 | D16: =A16 -> Kerala | E16: =GETPIVOTDATA("[Measures].[Sum of Sales]",$A$3,"[Zudio_sales_data].[State]","[Zudio_sales_data].[State].&[Kerala]") -> 172963.6
A17: Madhya Pradesh | B17: 419756 | D17: =A17 -> Madhya Pradesh | E17: =GETPIVOTDATA("[Measures].[Sum of Sales]",$A$3,"[Zudio_sales_data].[State]","[Zudio_sales_data].[State].&[Madhya Pradesh]") -> 419756
A18: Maharashtra | B18: 1941807.6 | D18: =A18 -> Maharashtra | E18: =GETPIVOTDATA("[Measures].[Sum of Sales]",$A$3,"[Zudio_sales_data].[State]","[Zudio_sales_data].[State].&[Maharashtra]") -> 1941807.6
A19: Puducherry | B19: 197334 | D19: =A19 -> Puducherry | E19: =GETPIVOTDATA("[Measures].[Sum of Sales]",$A$3,"[Zudio_sales_data].[State]","[Zudio_sales_data].[State].&[Puducherry]") -> 197334
A20: Rajasthan | B20: 208220.8 | D20: =A20 -> Rajasthan | E20: =GETPIVOTDATA("[Measures].[Sum of Sales]",$A$3,"[Zudio_sales_data].[State]","[Zudio_sales_data].[State].&[Rajasthan]") -> 208220.8
A21: Tamil Nadu | B21: 782751.6 | D21: =A21 -> Tamil Nadu | E21: =GETPIVOTDATA("[Measures].[Sum of Sales]",$A$3,"[Zudio_sales_data].[State]","[Zudio_sales_data].[State].&[Tamil Nadu]") -> 782751.6
A22: Telangana | B22: 236784.4 | D22: =A22 -> Telangana | E22: =GETPIVOTDATA("[Measures].[Sum of Sales]",$A$3,"[Zudio_sales_data].[State]","[Zudio_sales_data].[State].&[Telangana]") -> 236784.4
A23: Uttar Pradesh | B23: 1187057.6 | D23: =A23 -> Uttar Pradesh | E23: =GETPIVOTDATA("[Measures].[Sum of Sales]",$A$3,"[Zudio_sales_data].[State]","[Zudio_sales_data].[State].&[Uttar Pradesh]") -> 1187057.6
A24: West Bengal | B24: 218603.2 | D24: =A24 -> West Bengal | E24: =GETPIVOTDATA("[Measures].[Sum of Sales]",$A$3,"[Zudio_sales_data].[State]","[Zudio_sales_data].[State].&[West Bengal]") -> 218603.2
A25: Grand Total | B25: 8842540.4 | D25: =A25 -> Grand Total | E25: =GETPIVOTDATA("[Measures].[Sum of Sales]",$A$3) -> 8842540.4

Sheet city heat
A3: Row Labels | B3: Sum of Sales | D3: city | E3: sales
A4: Agra | B4: 173441.6 | D4: =A4 -> Agra | E4: =GETPIVOTDATA("[Measures].[Sum of Sales]",A4,"[Zudio_sales_data].[City]","[Zudio_sales_data].[City].&[Agra]") -> 173441.6
A5: Ahmedabad | B5: 240031.2 | D5: =A5 -> Ahmedabad | E5: =GETPIVOTDATA("[Measures].[Sum of Sales]",$A$3,"[Zudio_sales_data].[City]","[Zudio_sales_data].[City].&[Ahmedabad]") -> 240031.2
A6: Aurangabad | B6: 212798 | D6: =A6 -> Aurangabad | E6: =GETPIVOTDATA("[Measures].[Sum of Sales]",$A$3,"[Zudio_sales_data].[City]","[Zudio_sales_data].[City].&[Aurangabad]") -> 212798
A7: Bengaluru | B7: 191677.2 | D7: =A7 -> Bengaluru | E7: =GETPIVOTDATA("[Measures].[Sum of Sales]",$A$3,"[Zudio_sales_data].[City]","[Zudio_sales_data].[City].&[Bengaluru]") -> 191677.2
A8: Bhopal | B8: 253830.4 | D8: =A8 -> Bhopal | E8: =GETPIVOTDATA("[Measures].[Sum of Sales]",$A$3,"[Zudio_sales_data].[City]","[Zudio_sales_data].[City].&[Bhopal]") -> 253830.4
A9: Chandigarh | B9: 187812.8 | D9: =A9 -> Chandigarh | E9: =GETPIVOTDATA("[Measures].[Sum of Sales]",$A$3,"[Zudio_sales_data].[City]","[Zudio_sales_data].[City].&[Chandigarh]") -> 187812.8
A10: Chennai | B10: 265270 | D10: =A10 -> Chennai | E10: =GETPIVOTDATA("[Measures].[Sum of Sales]",$A$3,"[Zudio_sales_data].[City]","[Zudio_sales_data].[City].&[Chennai]") -> 265270
A11: Chhattisgarh | B11: 227924 | D11: =A11 -> Chhattisgarh | E11: =GETPIVOTDATA("[Measures].[Sum of Sales]",$A$3,"[Zudio_sales_data].[City]","[Zudio_sales_data].[City].&[Chhattisgarh]") -> 227924
A12: Coimbatore | B12: 292838 | D12: =A12 -> Coimbatore | E12: =GETPIVOTDATA("[Measures].[Sum of Sales]",$A$3,"[Zudio_sales_data].[City]","[Zudio_sales_data].[City].&[Coimbatore]") -> 292838
A13: Faridabad | B13: 214726 | D13: =A13 -> Faridabad | E13: =GETPIVOTDATA("[Measures].[Sum of Sales]",$A$3,"[Zudio_sales_data].[City]","[Zudio_sales_data].[City].&[Faridabad]") -> 214726
A14: Goa | B14: 203632.4 | D14: =A14 -> Goa | E14: =GETPIVOTDATA("[Measures].[Sum of Sales]",$A$3,"[Zudio_sales_data].[City]","[Zudio_sales_data].[City].&[Goa]") -> 203632.4
A15: Guwahati | B15: 211584 | D15: =A15 -> Guwahati | E15: =GETPIVOTDATA("[Measures].[Sum of Sales]",$A$3,"[Zudio_sales_data].[City]","[Zudio_sales_data].[City].&[Guwahati]") -> 211584
A16: Hyderabad | B16: 236784.4 | D16: =A16 -> Hyderabad | E16: =GETPIVOTDATA("[Measures].[Sum of Sales]",$A$3,"[Zudio_sales_data].[City]","[Zudio_sales_data].[City].&[Hyderabad]") -> 236784.4
A17: Indore | B17: 165925.6 | D17: =A17 -> Indore | E17: =GETPIVOTDATA("[Measures].[Sum of Sales]",$A$3,"[Zudio_sales_data].[City]","[Zudio_sales_data].[City].&[Indore]") -> 165925.6
A18: Jaipur | B18: 208220.8 | D18: =A18 -> Jaipur | E18: =GETPIVOTDATA("[Measures].[Sum of Sales]",$A$3,"[Zudio_sales_data].[City]","[Zudio_sales_data].[City].&[Jaipur]") -> 208220.8
A19: Jalna | B19: 251615.2 | D19: =A19 -> Jalna | E19: =GETPIVOTDATA("[Measures].[Sum of Sales]",$A$3,"[Zudio_sales_data].[City]","[Zudio_sales_data].[City].&[Jalna]") -> 251615.2
A20: Jammu | B20: 215214.4 | D20: =A20 -> Jammu | E20: =GETPIVOTDATA("[Measures].[Sum of Sales]",$A$3,"[Zudio_sales_data].[City]","[Zudio_sales_data].[City].&[Jammu]") -> 215214.4
A21: Kanpur | B21: 180632.8 | D21: =A21 -> Kanpur | E21: =GETPIVOTDATA("[Measures].[Sum of Sales]",$A$3,"[Zudio_sales_data].[City]","[Zudio_sales_data].[City].&[Kanpur]") -> 180632.8
A22: Kochi | B22: 172963.6 | D22: =A22 -> Kochi | E22: =GETPIVOTDATA("[Measures].[Sum of Sales]",$A$3,"[Zudio_sales_data].[City]","[Zudio_sales_data].[City].&[Kochi]") -> 172963.6
A23: Kolhapur | B23: 210026 | D23: =A23 -> Kolhapur | E23: =GETPIVOTDATA("[Measures].[Sum of Sales]",$A$3,"[Zudio_sales_data].[City]","[Zudio_sales_data].[City].&[Kolhapur]") -> 210026
A24: Kolkata | B24: 218603.2 | D24: =A24 -> Kolkata | E24: =GETPIVOTDATA("[Measures].[Sum of Sales]",$A$3,"[Zudio_sales_data].[City]","[Zudio_sales_data].[City].&[Kolkata]") -> 218603.2
A25: Lucknow | B25: 211228 | D25: =A25 -> Lucknow | E25: =GETPIVOTDATA("[Measures].[Sum of Sales]",$A$3,"[Zudio_sales_data].[City]","[Zudio_sales_data].[City].&[Lucknow]") -> 211228
A26: Madurai | B26: 224643.6 | D26: =A26 -> Madurai | E26: =GETPIVOTDATA("[Measures].[Sum of Sales]",$A$3,"[Zudio_sales_data].[City]","[Zudio_sales_data].[City].&[Madurai]") -> 224643.6
A27: Meerut | B27: 217478.4 | D27: =A27 -> Meerut | E27: =GETPIVOTDATA("[Measures].[Sum of Sales]",$A$3,"[Zudio_sales_data].[City]","[Zudio_sales_data].[City].&[Meerut]") -> 217478.4
A28: Mumbai | B28: 136612 | D28: =A28 -> Mumbai | E28: =GETPIVOTDATA("[Measures].[Sum of Sales]",$A$3,"[Zudio_sales_data].[City]","[Zudio_sales_data].[City].&[Mumbai]") -> 136612
A29: Mysuru | B29: 232558.4 | D29: =A29 -> Mysuru | E29: =GETPIVOTDATA("[Measures].[Sum of Sales]",$A$3,"[Zudio_sales_data].[City]","[Zudio_sales_data].[City].&[Mysuru]") -> 232558.4
A30: Nagpur | B30: 183591.6 | D30: =A30 -> Nagpur | E30: =GETPIVOTDATA("[Measures].[Sum of Sales]",$A$3,"[Zudio_sales_data].[City]","[Zudio_sales_data].[City].&[Nagpur]") -> 183591.6
A31: Nashik | B31: 184724.4 | D31: =A31 -> Nashik | E31: =GETPIVOTDATA("[Measures].[Sum of Sales]",$A$3,"[Zudio_sales_data].[City]","[Zudio_sales_data].[City].&[Nashik]") -> 184724.4
A32: New Delhi | B32: 228078.4 | D32: =A32 -> New Delhi | E32: =GETPIVOTDATA("[Measures].[Sum of Sales]",$A$3,"[Zudio_sales_data].[City]","[Zudio_sales_data].[City].&[New Delhi]") -> 228078.4
A33: Noida | B33: 191889.6 | D33: =A33 -> Noida | E33: =GETPIVOTDATA("[Measures].[Sum of Sales]",$A$3,"[Zudio_sales_data].[City]","[Zudio_sales_data].[City].&[Noida]") -> 191889.6
A34: Patna | B34: 211697.6 | D34: =A34 -> Patna | E34: =GETPIVOTDATA("[Measures].[Sum of Sales]",$A$3,"[Zudio_sales_data].[City]","[Zudio_sales_data].[City].&[Patna]") -> 211697.6
A35: Pondicherry | B35: 197334 | D35: =A35 -> Pondicherry | E35: =GETPIVOTDATA("[Measures].[Sum of Sales]",$A$3,"[Zudio_sales_data].[City]","[Zudio_sales_data].[City].&[Pondicherry]") -> 197334
A36: Pune | B36: 195982 | D36: =A36 -> Pune | E36: =GETPIVOTDATA("[Measures].[Sum of Sales]",$A$3,"[Zudio_sales_data].[City]","[Zudio_sales_data].[City].&[Pune]") -> 195982
A37: Rajkot | B37: 270530.8 | D37: =A37 -> Rajkot | E37: =GETPIVOTDATA("[Measures].[Sum of Sales]",$A$3,"[Zudio_sales_data].[City]","[Zudio_sales_data].[City].&[Rajkot]") -> 270530.8
A38: Ranchi | B38: 217012 | D38: =A38 -> Ranchi | E38: =GETPIVOTDATA("[Measures].[Sum of Sales]",$A$3,"[Zudio_sales_data].[City]","[Zudio_sales_data].[City].&[Ranchi]") -> 217012
A39: Satara | B39: 199460.8 | D39: =A39 -> Satara | E39: =GETPIVOTDATA("[Measures].[Sum of Sales]",$A$3,"[Zudio_sales_data].[City]","[Zudio_sales_data].[City].&[Satara]") -> 199460.8
A40: Solapur | B40: 177992.8 | D40: =A40 -> Solapur | E40: =GETPIVOTDATA("[Measures].[Sum of Sales]",$A$3,"[Zudio_sales_data].[City]","[Zudio_sales_data].[City].&[Solapur]") -> 177992.8
A41: Surat | B41: 213316 | D41: =A41 -> Surat | E41: =GETPIVOTDATA("[Measures].[Sum of Sales]",$A$3,"[Zudio_sales_data].[City]","[Zudio_sales_data].[City].&[Surat]") -> 213316
A42: Thane | B42: 189004.8 | D42: =A42 -> Thane | E42: =GETPIVOTDATA("[Measures].[Sum of Sales]",$A$3,"[Zudio_sales_data].[City]","[Zudio_sales_data].[City].&[Thane]") -> 189004.8
A43: Vadodara | B43: 198012.4 | D43: =A43 -> Vadodara | E43: =GETPIVOTDATA("[Measures].[Sum of Sales]",$A$3,"[Zudio_sales_data].[City]","[Zudio_sales_data].[City].&[Vadodara]") -> 198012.4
A44: Varanasi | B44: 212387.2 | D44: =A44 -> Varanasi | E44: =GETPIVOTDATA("[Measures].[Sum of Sales]",$A$3,"[Zudio_sales_data].[City]","[Zudio_sales_data].[City].&[Visakhapatnam]") -> 213454
A45: Visakhapatnam | B45: 213454 | D45: =A45 -> Visakhapatnam | E45: =GETPIVOTDATA("[Measures].[Sum of Sales]",$A$3,"[Zudio_sales_data].[City]","[Zudio_sales_data].[City].&[Visakhapatnam]") -> 213454
A46: Grand Total | B46: 8842540.4 | D46: =A46 -> Grand Total | E46: =GETPIVOTDATA("[Measures].[Sum of Sales]",$A$3) -> 8842540.4

Sheet rank kpi
A2: Row Labels | B2: Sum of Sales | D2: rank column | E2: performance
A3: Coimbatore | B3: 292838 | D3: =_xlfn.RANK.EQ(GETPIVOTDATA("[Measures].[Sum of Sales]",$A$2,"[Zudio_sales_data].[City]","[Zudio_sales_data].[City].&["&A3&"]"),$B$3:$B$44,0) -> 1 | E3: =IF(D3<=3,"High",IF(D3<=7,"Medium","Low")) -> High
A4: Rajkot | B4: 270530.8 | D4: =_xlfn.RANK.EQ(GETPIVOTDATA("[Measures].[Sum of Sales]",$A$2,"[Zudio_sales_data].[City]","[Zudio_sales_data].[City].&["&A4&"]"),$B$3:$B$44,0) -> 2 | E4: =IF(D4<=3,"High",IF(D4<=7,"Medium","Low")) -> High
A5: Chennai | B5: 265270 | D5: =_xlfn.RANK.EQ(GETPIVOTDATA("[Measures].[Sum of Sales]",$A$2,"[Zudio_sales_data].[City]","[Zudio_sales_data].[City].&["&A5&"]"),$B$3:$B$44,0) -> 3 | E5: =IF(D5<=3,"High",IF(D5<=7,"Medium","Low")) -> High
A6: Bhopal | B6: 253830.4 | D6: =_xlfn.RANK.EQ(GETPIVOTDATA("[Measures].[Sum of Sales]",$A$2,"[Zudio_sales_data].[City]","[Zudio_sales_data].[City].&["&A6&"]"),$B$3:$B$44,0) -> 4 | E6: =IF(D6<=3,"High",IF(D6<=7,"Medium","Low")) -> Medium
A7: Jalna | B7: 251615.2 | D7: =_xlfn.RANK.EQ(GETPIVOTDATA("[Measures].[Sum of Sales]",$A$2,"[Zudio_sales_data].[City]","[Zudio_sales_data].[City].&["&A7&"]"),$B$3:$B$44,0) -> 5 | E7: =IF(D7<=3,"High",IF(D7<=7,"Medium","Low")) -> Medium
A8: Ahmedabad | B8: 240031.2 | D8: =_xlfn.RANK.EQ(GETPIVOTDATA("[Measures].[Sum of Sales]",$A$2,"[Zudio_sales_data].[City]","[Zudio_sales_data].[City].&["&A8&"]"),$B$3:$B$44,0) -> 6 | E8: =IF(D8<=3,"High",IF(D8<=7,"Medium","Low")) -> Medium
A9: Hyderabad | B9: 236784.4 | D9: =_xlfn.RANK.EQ(GETPIVOTDATA("[Measures].[Sum of Sales]",$A$2,"[Zudio_sales_data].[City]","[Zudio_sales_data].[City].&["&A9&"]"),$B$3:$B$44,0) -> 7 | E9: =IF(D9<=3,"High",IF(D9<=7,"Medium","Low")) -> Medium
A10: Mysuru | B10: 232558.4 | D10: =_xlfn.RANK.EQ(GETPIVOTDATA("[Measures].[Sum of Sales]",$A$2,"[Zudio_sales_data].[City]","[Zudio_sales_data].[City].&["&A10&"]"),$B$3:$B$44,0) -> 8 | E10: =IF(D10<=3,"High",IF(D10<=7,"Medium","Low")) -> Low
A11: New Delhi | B11: 228078.4 | D11: =_xlfn.RANK.EQ(GETPIVOTDATA("[Measures].[Sum of Sales]",$A$2,"[Zudio_sales_data].[City]","[Zudio_sales_data].[City].&["&A11&"]"),$B$3:$B$44,0) -> 9 | E11: =IF(D11<=3,"High",IF(D11<=7,"Medium","Low")) -> Low
A12: Chhattisgarh | B12: 227924 | D12: =_xlfn.RANK.EQ(GETPIVOTDATA("[Measures].[Sum of Sales]",$A$2,"[Zudio_sales_data].[City]","[Zudio_sales_data].[City].&["&A12&"]"),$B$3:$B$44,0) -> 10 | E12: =IF(D12<=3,"High",IF(D12<=7,"Medium","Low")) -> Low
A13: Madurai | B13: 224643.6 | D13: =_xlfn.RANK.EQ(GETPIVOTDATA("[Measures].[Sum of Sales]",$A$2,"[Zudio_sales_data].[City]","[Zudio_sales_data].[City].&["&A13&"]"),$B$3:$B$44,0) -> 11 | E13: =IF(D13<=3,"High",IF(D13<=7,"Medium","Low")) -> Low
A14: Kolkata | B14: 218603.2 | D14: =_xlfn.RANK.EQ(GETPIVOTDATA("[Measures].[Sum of Sales]",$A$2,"[Zudio_sales_data].[City]","[Zudio_sales_data].[City].&["&A14&"]"),$B$3:$B$44,0) -> 12 | E14: =IF(D14<=3,"High",IF(D14<=7,"Medium","Low")) -> Low
... A44: Mumbai | B44: 136612 | D44: =_xlfn.RANK.EQ(GETPIVOTDATA("[Measures].[Sum of Sales]",$A$2,"[Zudio_sales_data].[City]","[Zudio_sales_data].[City].&["&A44&"]"),$B$3:$B$44,0) -> 42 | E44: =IF(D44<=3,"High",IF(D44<=7,"Medium","Low")) -> Low
A45: Grand Total | B45: 8842540.4

Sheet Sheet9
A3: Row Labels | B3: Sum of Sales
A4: 1 | B4: 90884.4
A5: 10 | B5: 85810
A6: 100 | B6: 129648
A7: 11 | B7: 74319.2
A8: 12 | B8: 70313.6
A9: 13 | B9: 102809.6
A10: 14 | B10: 121893.2
A11: 15 | B11: 82644.8
A12: 16 | B12: 60924.8
A13: 17 | B13: 102812.4
A14: 18 | B14: 116789.2
A15: 19 | B15: 106598
... A104: Grand Total | B104: 8842540.4

Sheet Sheet2

Sheet Sheet4
A3: Row Labels | B3: Sum of Sales
A4: Coimbatore | B4: 292838
A5: Rajkot | B5: 270530.8
A6: Chennai | B6: 265270
A7: Bhopal | B7: 253830.4
A8: Jalna | B8: 251615.2
A9: Ahmedabad | B9: 240031.2
A10: Hyderabad | B10: 236784.4
A11: Mysuru | B11: 232558.4
A12: New Delhi | B12: 228078.4
A13: Chhattisgarh | B13: 227924
A14: Grand Total | B14: 2499460.8

Sheet Sheet5
A3: Row Labels | B3: Sum of Sales
A4: Maharashtra | B4: 1941807.6
A5: Uttar Pradesh | B5: 1187057.6
A6: Gujarat | B6: 921890.4
A7: Tamil Nadu | B7: 782751.6
A8: Karnataka | B8: 424235.6
A9: Madhya Pradesh | B9: 419756
A10: Telangana | B10: 236784.4
A11: Delhi | B11: 228078.4
A12: Chhattisgarh | B12: 227924
A13: West Bengal | B13: 218603.2
A14: Jharkhand | B14: 217012
A15: Jammu and Kashmir | B15: 215214.4
... A25: Grand Total | B25: 8842540.4

Sheet Zudio_sales_data
A1: State | B1: City | C1: Category | D1: Clothing Type | E1: Store Number | F1: Postal Code | G1: Store Type | H1: Store Open Date | I1: Selling Area Size | J1: Store Manager | K1: Manager ID | L1: Store Address | M1: Contact Type | N1: Final Contact | O1: Operating Hours | P1: Staff Count | Q1: Parking Availability | R1: Security Features | S1: Order ID | T1: Order Date | U1: Month No | V1: Month | W1: Customer ID | X1: Customer Name | Y1: Product ID | Z1: Price | AA1: Quantity | AB1: Sales | AC1: Order Value avg | AD1: Assumed margin | AE1: Estimated profit | AF1: Profit margin | AG1: Sales_Display
A2: Karnataka | B2: Bengaluru | C2: Women | D2: Tops | E2: 15 | F2: 424173 | G2: Rented | H2: 44347 | I2: 1100 | J2: Donald Horton | K2: M27 | L2: Unit 5604 Box 6098 DPO AP 20626 | M2: Mobile | N2: 7897488733 | O2: 11 AM - 8 PM | P2: 13 | Q2: Not Available | R2: CCTV, Alarm | S2: 77434 | T2: 45309 | U2: 1 | V2: Jan | W2: 291736 | X2: Donna Rodriguez | Y2: 693 | Z2: 1764 | AA2: 1 | AB2: 705.6 | AC2: 705.6 | AD2: 0.35 | AE2: 246.96 | AF2: 0.35 | AG2: =IF(AB2>=100000,"₹"&TEXT(AB2/100000,"0.0")&" L", IF(AB2>=1000,"₹"&TEXT(AB2/1000,"0")&" K", "₹"&AB2)) -> ₹705.6
A3: Uttar Pradesh | B3: Kanpur | C3: Women | D3: Jackets | E3: 95 | F3: 420930 | G3: Owned | H3: 44198 | I3: 1100 | J3: Monique Harris | K3: M37 | L3: USCGC Williams FPO AA 72236 | M3: Landline | N3: 2413227659 | O3: 9 AM - 8 PM | P3: 7 | Q3: Available | R3: CCTV, Alarm | S3: 68727 | T3: 45315 | U3: 1 | V3: Jan | W3: 947806 | X3: Susan Hill | Y3: 675 | Z3: 1740 | AA3: 6 | AB3: 4176 | AC3: 696 | AD3: 0.35 | AE3: 1461.6 | AF3: 0.35 | AG3: =IF(AB3>=100000,"₹"&TEXT(AB3/100000,"0.0")&" L", IF(AB3>=1000,"₹"&TEXT(AB3/1000,"0")&" K", "₹"&AB3)) -> ₹4 K
A4: Gujarat | B4: Surat | C4: Kids | D4: Sweaters | E4: 7 | F4: 426430 | G4: Owned | H4: 45082 | I4: 1300 | J4: Tammy Martinez | K4: M91 | L4: 57812 Rhonda Stream Suite 602 New Daniel, SC 99084 | M4: Mobile | N4: 9933662107 | O4: 10 AM - 9 PM | P4: 6 | Q4: Not Available | R4: None | S4: 59759 | T4: 45296 | U4: 1 | V4: Jan | W4: 438133 | X4: Jennifer Blanchard | Y4: 515 | Z4: 1889 | AA4: 6 | AB4: 4533.6 | AC4: 755.6 | AD4: 0.28 | AE4: 1269.408 | AF4: 0.28 | AG4: =IF(AB4>=100000,"₹"&TEXT(AB4/100000,"0.0")&" L", IF(AB4>=1000,"₹"&TEXT(AB4/1000,"0")&" K", "₹"&AB4)) -> ₹5 K
A5: Maharashtra | B5: Nashik | C5: Kids | D5: Tops | E5: 97 | F5: 407331 | G5: Rented | H5: 45320 | I5: 1400 | J5: Mr. Jacob Miles | K5: M95 | L5: 6479 Christine Mountains Perezchester, AZ 35887 | M5: Mobile | N5: 6621983194 | O5: 10 AM - 7 PM | P5: 4 | Q5: Not Available | R5: CCTV, Alarm | S5: 35297 | T5: 45292 | U5: 1 | V5: Jan | W5: 237215 | X5: Erica Hughes | Y5: 459 | Z5: 1200 | AA5: 1 | AB5: 480 | AC5: 480 | AD5: 0.28 | AE5: 134.4 | AF5: 0.28 | AG5: =IF(AB5>=100000,"₹"&TEXT(AB5/100000,"0.0")&" L", IF(AB5>=1000,"₹"&TEXT(AB5/1000,"0")&" K", "₹"&AB5)) -> ₹480
A6: Uttar Pradesh | B6: Agra | C6: Men | D6: Shirts | E6: 19 | F6: 406436 | G6: Rented | H6: 45371 | I6: 1300 | J6: Peter Eaton | K6: M71 | L6: Unit 9188 Box 1212 DPO AE 45339 | M6: Mobile | N6: 9670204374 | O6: 10 AM - 9 PM | P6: 13 | Q6: Available | R6: CCTV | S6: 42774 | T6: 45315 | U6: 1 | V6: Jan | W6: 859669 | X6: Joshua Sanders | Y6: 395 | Z6: 2354 | AA6: 4 | AB6: 3766.4 | AC6: 941.6 | AD6: 0.22 | AE6: 828.608 | AF6: 0.22 | AG6: =IF(AB6>=100000,"₹"&TEXT(AB6/100000,"0.0")&" L", IF(AB6>=1000,"₹"&TEXT(AB6/1000,"0")&" K", "₹"&AB6)) -> ₹4 K
A7: Uttar Pradesh | B7: Noida | C7: Men | D7: Hoodies | E7: 85 | F7: 415176 | G7: Rented | H7: 43909 | I7: 1400 | J7: Corey Jones | K7: M34 | L7: 43535 Wilson Crescent Suite 738 Mcbrideton, FL 72870 | M7: Landline | N7: 5638588246 | O7: 10 AM - 9 PM | P7: 4 | Q7: Available | R7: CCTV, Alarm | S7: 51791 | T7: 45318 | U7: 1 | V7: Jan | W7: 635475 | X7: Thomas Garcia | Y7: 811 | Z7: 1441 | AA7: 2 | AB7: 1152.8 | AC7: 576.4 | AD7: 0.22 | AE7: 253.616 | AF7: 0.22 | AG7: =IF(AB7>=100000,"₹"&TEXT(AB7/100000,"0.0")&" L", IF(AB7>=1000,"₹"&TEXT(AB7/1000,"0")&" K", "₹"&AB7)) -> ₹1 K
A8: Maharashtra | B8: Solapur | C8: Men | D8: Shirts | E8: 72 | F8: 401352 | G8: Owned | H8: 44132 | I8: 800 | J8: James Davis | K8: M32 | L8: Unit 4022 Box 1237 DPO AA 68513 | M8: Landline | N8: 2680493541 | O8: 11 AM - 8 PM | P8: 6 | Q8: Available | R8: CCTV | S8: 68620 | T8: 45297 | U8: 1 | V8: Jan | W8: 455328 | X8: Nina Williams | Y8: 425 | Z8: 2063 | AA8: 5 | AB8: 4126 | AC8: 825.2 | AD8: 0.22 | AE8: 907.72 | AF8: 0.22 | AG8: =IF(AB8>=100000,"₹"&TEXT(AB8/100000,"0.0")&" L", IF(AB8>=1000,"₹"&TEXT(AB8/1000,"0")&" K", "₹"&AB8)) -> ₹4 K
A9: Madhya Pradesh | B9: Indore | C9: Women | D9: Sweaters | E9: 27 | F9: 403527 | G9: Owned | H9: 44416 | I9: 950 | J9: John Glass | K9: M15 | L9: 07221 Walker Mountains North Barbaraview, NH 19535 | M9: Mobile | N9: 9047487917 | O9: 9 AM - 8 PM | P9: 9 | Q9: Not Available | R9: None | S9: 88095 | T9: 45307 | U9: 1 | V9: Jan | W9: 491912 | X9: Teresa Carpenter | Y9: 754 | Z9: 1854 | AA9: 7 | AB9: 5191.2 | AC9: 741.6 | AD9: 0.35 | AE9: 1816.92 | AF9: 0.35 | AG9: =IF(AB9>=100000,"₹"&TEXT(AB9/100000,"0.0")&" L", IF(AB9>=1000,"₹"&TEXT(AB9/1000,"0")&" K", "₹"&AB9)) -> ₹5 K
A10: Uttar Pradesh | B10: Kanpur | C10: Women | D10: Skirts | E10: 20 | F10: 428113 | G10: Rented | H10: 44749 | I10: 1400 | J10: Amanda Melendez | K10: M76 | L10: PSC 8289, Box 1036 APO AE 23193 | M10: Landline | N10: 4631690104 | O10: 10 AM - 7 PM | P10: 14 | Q10: Available | R10: CCTV | S10: 52094 | T10: 45294 | U10: 1 | V10: Jan | W10: 949679 | X10: Jeff Jackson | Y10: 332 | Z10: 2627 | AA10: 3 | AB10: 3152.4 | AC10: 1050.8 | AD10: 0.35 | AE10: 1103.34 | AF10: 0.35 | AG10: =IF(AB10>=100000,"₹"&TEXT(AB10/100000,"0.0")&" L", IF(AB10>=1000,"₹"&TEXT(AB10/1000,"0")&" K", "₹"&AB10)) -> ₹3 K
A11: Gujarat | B11: Ahmedabad | C11: Men | D11: Shirts | E11: 81 | F11: 401791 | G11: Owned | H11: 43982 | I11: 1000 | J11: Donna Clark | K11: M97 | L11: 9997 Miller Passage Port Madisonhaven, AL 61509 | M11: Landline | N11: 1605702469 | O11: 11 AM - 8 PM | P11: 14 | Q11: Not Available | R11: Alarm | S11: 47656 | T11: 45309 | U11: 1 | V11: Jan | W11: 869378 | X11: Alexander Parsons | Y11: 841 | Z11: 2689 | AA11: 6 | AB11: 6453.6 | AC11: 1075.6 | AD11: 0.22 | AE11: 1419.792 | AF11: 0.22 | AG11: =IF(AB11>=100000,"₹"&TEXT(AB11/100000,"0.0")&" L", IF(AB11>=1000,"₹"&TEXT(AB11/1000,"0")&" K", "₹"&AB11)) -> ₹6 K
A12: Delhi | B12: New Delhi | C12: Kids | D12: T-Shirts | E12: 4 | F12: 416365 | G12: Rented | H12: 45011 | I12: 1400 | J12: Alexander Jones | K12: M46 | L12: 747 Mejia Harbor Timothychester, GA 16657 | M12: Mobile | N12: 6281054738 | O12: 10 AM - 7 PM | P12: 3 | Q12: Not Available | R12: Alarm | S12: 63250 | T12: 45297 | U12: 1 | V12: Jan | W12: 933335 | X12: Yvette Thomas | Y12: 306 | Z12: 1085 | AA12: 3 | AB12: 1302 | AC12: 434 | AD12: 0.28 | AE12: 364.56 | AF12: 0.28 | AG12: =IF(AB12>=100000,"₹"&TEXT(AB12/100000,"0.0")&" L", IF(AB12>=1000,"₹"&TEXT(AB12/1000,"0")&" K", "₹"&AB12)) -> ₹1 K
A13: Assam | B13: Guwahati | C13: Men | D13: Skirts | E13: 7 | F13: 424941 | G13: Owned | H13: 44726 | I13: 1200 | J13: Christopher Cole | K13: M52 | L13: 433 Shaw Key New Aaron, WY 46337 | M13: Mobile | N13: 9184967171 | O13: 10 AM - 9 PM | P13: 20 | Q13: Not Available | R13: Alarm | S13: 75992 | T13: 45306 | U13: 1 | V13: Jan | W13: 774455 | X13: Lauren Romero | Y13: 386 | Z13: 2177 | AA13: 7 | AB13: 6095.6 | AC13: 870.8 | AD13: 0.22 | AE13: 1341.032 | AF13: 0.22 | AG13: =IF(AB13>=100000,"₹"&TEXT(AB13/100000,"0.0")&" L", IF(AB13>=1000,"₹"&TEXT(AB13/1000,"0")&" K", "₹"&AB13)) -> ₹6 K
... A2780: Haryana | B2780: Faridabad | C2780: Men | D2780: T-Shirts | E2780: 28 | F2780: 434195 | G2780: Rented | H2780: 44026 | I2780: 950 | J2780: Jose Gomez | K2780: M80 | L2780: 2158 Tran Hill Stewartport, RI 93029 | M2780: Landline | N2780: 3551204713 | O2780: 11 AM - 8 PM | P2780: 19 | Q2780: Not Available | R2780: None | S2780: 59545 | T2780: 45629 | U2780: 12 | V2780: Dec | W2780: 256723 | X2780: Crystal Hernandez | Y2780: 511 | Z2780: 2325 | AA2780: 4 | AB2780: 3720 | AC2780: 930 | AD2780: 0.22 | AE2780: 818.4 | AF2780: 0.22 | AG2780: =IF(AB2780>=100000,"₹"&TEXT(AB2780/100000,"0.0")&" L", IF(AB2780>=1000,"₹"&TEXT(AB2780/1000,"0")&" K", "₹"&AB2780)) -> ₹4 K

Sheet Dashboard layout
AN28: =GETPIVOTDATA("Sales",'kpi linechart'!$A$3) -> 8842540.4
AN31: =GETPIVOTDATA("[Measures].[Sum of Sales]",Sheet3!$A$3) -> 8842540.4
AN34: =GETPIVOTDATA("[Measures].[Sum of Quantity]",Sheet3!$B$3) -> 12572
AN37: =GETPIVOTDATA("[Measures].[Count of Order ID]",Sheet3!$C$3) -> 2779 | AQ37: =GETPIVOTDATA("Sales",'kpi linechart'!$A$3) -> 8842540.4
AN39: =Sheet3!A6 -> 8842540.4 | AQ39: =GETPIVOTDATA("Quantity",'kpi linechart'!$B$3) -> 12572
AQ41: =GETPIVOTDATA("Order ID",'kpi linechart'!$C$3) -> 2779
AQ43: ='kpi linechart'!D4 -> 3181.9145
AQ45: =GETPIVOTDATA("[Measures].[Distinct Count of Store Number]",'kpi linechart'!$E$3) -> 100
AQ47: =GETPIVOTDATA("[Measures].[Sum of Assumed margin]",'kpi linechart'!$F$3) -> #REF!
AQ50: =GETPIVOTDATA("[Measures].[Average of Assumed margin]",'kpi linechart'!$F$3) -> 0.2824973

Sheet Sheet1
A1: City | B1: Correct State
A2: Agra | B2: Uttar Pradesh
A3: Ahmedabad | B3: Gujarat
A4: Aurangabad | B4: Maharashtra
A5: Bengaluru | B5: Karnataka
A6: Bhopal | B6: Madhya Pradesh
A7: Chandigarh | B7: Chandigarh
A8: Chennai | B8: Tamil Nadu
A9: Chhattisgarh | B9: Chhattisgarh
A10: Coimbatore | B10: Tamil Nadu
A11: Faridabad | B11: Haryana
A12: Goa | B12: Goa
... A43: Visakhapatnam | B43: Andhra Pradesh

Sheet Sheet3
A3: Sum of Sales | B3: Sum of Quantity | C3: Count of Order ID
A4: 8842540.4 | B4: 12572 | C4: 2779
A6: =GETPIVOTDATA("[Measures].[Sum of Sales]",$A$3) -> 8842540.4
D15: =GETPIVOTDATA("[Measures].[Sum of Sales]",$A$3) -> 8842540.4
